Workbook

Sheet P&L Gerencial
A1: PERU ON ICE S.A.C. — P&L GERENCIAL 2025 (SIN IGV)
A2: RUC: 20613509446 | Moneda: S/ Soles | Sin IGV | Ejercicio: Enero–Diciembre 2025
A4: CONCEPTO | B4: CTA. | C4: ENE | D4: FEB | E4: MAR | F4: ABR | G4: MAY | H4: JUN | I4: JUL | J4: AGO | K4: SET | L4: OCT | M4: NOV | N4: DIC | O4: TOTAL ANUAL | P4: % REV.
A5: A. INGRESOS
A6: Ingresos por Servicios de Pista | B6: 7032100 | C6: 192370.04 | D6: 214297.38 | E6: 159044.24 | F6: 162394.91 | G6: 146655.75 | H6: 148722.4 | I6: 185458.76 | J6: 177730.07 | K6: 139427.16 | L6: 144036.01 | M6: 140103.32 | N6: 192603.92 | O6: =SUM(C6:N6) -> 2002844 | P6: =IFERROR(O6/O6,0) -> 1
A7: ► Ticket Promedio
A8: TOTAL INGRESOS | C8: =C6 -> 192370.04 | D8: =D6 -> 214297.38 | E8: =E6 -> 159044.24 | F8: =F6 -> 162394.91 | G8: =G6 -> 146655.75 | H8: =H6 -> 148722.4 | I8: =I6 -> 185458.76 | J8: =J6 -> 177730.07 | ... N8: =N6 -> 192603.92 | O8: =SUM(C8:N8) -> 2002844 | P8: =IFERROR(O8/O6,0) -> 1
A10: B. COSTOS OPERATIVOS DEL HIELO
A11: Energía Eléctrica | B11: 6361100 | C11: 22754.51 | D11: 24839.76 | E11: 23204.47 | F11: 22781.98 | G11: 20410.69 | H11: 18773.92 | I11: 17726.41 | J11: 17115.76 | K11: 17788.04 | L11: 16850.1 | M11: 17318.98 | N11: 18987.72 | O11: =SUM(C11:N11) -> 238552.34 | P11: =IFERROR(O11/O6,0) -> 0.1191068
A12: Alquiler Chiller (Refrigeración) | B12: 6352101 | C12: 19000 | D12: 19000 | E12: 0 | F12: 19000 | G12: 19000 | H12: 19000 | I12: 19000 | J12: 19000 | K12: 19000 | L12: 19000 | M12: 19000 | N12: 19000 | O12: =SUM(C12:N12) -> 209000 | P12: =IFERROR(O12/O6,0) -> 0.10435161
A13: Agua | B13: 6363100 | C13: 1097.03 | D13: 1043.05 | E13: 837.89 | F13: 676.25 | G13: 783.81 | H13: 621.87 | I13: 438.81 | J13: 524.66 | K13: 582.14 | L13: 473.18 | M13: 624.77 | N13: 470.98 | O13: =SUM(C13:N13) -> 8174.44 | P13: =IFERROR(O13/O6,0) -> 0.0040814163
A14: Mantenimiento Local | B14: 6341101 | C14: 100 | D14: 0 | E14: 135.59 | F14: 1800 | G14: 950 | H14: 350 | I14: 596.95 | J14: 930 | K14: 14665.22 | L14: 700 | M14: 2076.02 | N14: 0 | O14: =SUM(C14:N14) -> 22303.78 | P14: =IFERROR(O14/O6,0) -> 0.011136055
A15: Mant. Prop. Planta y Equipo | B15: 6343100 | C15: 250 | D15: 0 | E15: 0 | F15: 0 | G15: 0 | H15: 0 | I15: 1000 | J15: 0 | K15: 2450 | L15: 0 | M15: 0 | N15: 0 | O15: =SUM(C15:N15) -> 3700 | P15: =IFERROR(O15/O6,0) -> 0.0018473731
A16: Servicio de Patinaje | B16: 6381115 | C16: 500 | D16: 0 | E16: 0 | F16: 0 | G16: 0 | H16: 0 | I16: 360 | J16: 600 | K16: 0 | L16: 0 | M16: 0 | N16: 0 | O16: =SUM(C16:N16) -> 1460 | P16: =IFERROR(O16/O6,0) -> 0.00072896343
A17: Servicio Tópico (Enfermería) | B17: 6381117 | C17: 560 | D17: 240 | E17: 640 | F17: 1381.44 | G17: 620 | H17: 0 | I17: 1569.92 | J17: 500 | K17: 291.95 | L17: 340 | M17: 1107.63 | N17: 300 | O17: =SUM(C17:N17) -> 7550.94 | P17: =IFERROR(O17/O6,0) -> 0.003770109
A18: Suministros Operativos | B18: 6561100 | C18: 2449.14 | D18: 135.59 | E18: 2237.28 | F18: 0 | G18: 0 | H18: 720.34 | I18: 0 | J18: 369.49 | K18: 0 | L18: 779.65 | M18: 0 | N18: 1864.39 | O18: =SUM(C18:N18) -> 8555.88 | P18: =IFERROR(O18/O6,0) -> 0.0042718655
A19: Útiles de Aseo | B19: 6561103 | C19: 0 | D19: 5.08 | E19: 1255.09 | F19: 1186.44 | G19: 0 | H19: 1016.1 | I19: 919.41 | J19: 933.05 | K19: 392.37 | L19: 722.03 | M19: 922.89 | N19: 0 | O19: =SUM(C19:N19) -> 7352.46 | P19: =IFERROR(O19/O6,0) -> 0.0036710099
A20: Artículos de Ferretería | B20: 6561104 | C20: 409.16 | D20: 110.08 | E20: 718.21 | F20: 244.5 | G20: 144.06 | H20: 10.17 | I20: 382.29 | J20: 630.51 | K20: 158.06 | L20: 25.42 | M20: 985.15 | N20: 33.9 | O20: =SUM(C20:N20) -> 3851.51 | P20: =IFERROR(O20/O6,0) -> 0.0019230205
A21: Botiquín | B21: 6561106 | C21: 61.86 | D21: 212.12 | E21: 0 | F21: 0 | G21: 14.49 | H21: 31.02 | I21: 59.91 | J21: 19.57 | K21: 25.42 | L21: 0 | M21: 0 | N21: 304.66 | O21: =SUM(C21:N21) -> 729.05 | P21: =IFERROR(O21/O6,0) -> 0.00036400739
A22: Gastos a Reparar | B22: 6591104 | C22: 1213 | D22: 22 | E22: 0 | F22: 78.36 | G22: 402 | H22: 200 | I22: 24 | J22: 0 | K22: 1728.1 | L22: 0 | M22: 0 | N22: 0 | O22: =SUM(C22:N22) -> 3667.46 | P22: =IFERROR(O22/O6,0) -> 0.0018311262
A23: Uniformes | B23: 6591105 | C23: 130 | D23: 0 | E23: 172.88 | F23: 72 | G23: 49.66 | H23: 0 | I23: 130.51 | J23: 0 | K23: 0 | L23: 0 | M23: 0 | N23: 0 | O23: =SUM(C23:N23) -> 555.05 | P23: =IFERROR(O23/O6,0) -> 0.00027713093
A24: TOTAL COSTOS OPERATIVOS DEL HIELO | C24: =C11+C12+C13+C14+C15+C16+C17+C18+C19+C20+C21+C22+C23 -> 48524.7 | D24: =D11+D12+D13+D14+D15+D16+D17+D18+D19+D20+D21+D22+D23 -> 45607.68 | E24: =E11+E12+E13+E14+E15+E16+E17+E18+E19+E20+E21+E22+E23 -> 29201.41 | F24: =F11+F12+F13+F14+F15+F16+F17+F18+F19+F20+F21+F22+F23 -> 47220.97 | G24: =G11+G12+G13+G14+G15+G16+G17+G18+G19+G20+G21+G22+G23 -> 42374.71 | H24: =H11+H12+H13+H14+H15+H16+H17+H18+H19+H20+H21+H22+H23 -> 40723.42 | I24: =I11+I12+I13+I14+I15+I16+I17+I18+I19+I20+I21+I22+I23 -> 42208.21 | J24: =J11+J12+J13+J14+J15+J16+J17+J18+J19+J20+J21+J22+J23 -> 40623.04 | ... N24: =N11+N12+N13+N14+N15+N16+N17+N18+N19+N20+N21+N22+N23 -> 40961.65 | O24: =SUM(C24:N24) -> 515452.91 | P24: =IFERROR(O24/O6,0) -> 0.25736049
A25: ★ UTILIDAD BRUTA OPERATIVA (A − B) | C25: =C8-C24 -> 143845.34 | D25: =D8-D24 -> 168689.7 | E25: =E8-E24 -> 129842.83 | F25: =F8-F24 -> 115173.94 | G25: =G8-G24 -> 104281.04 | H25: =H8-H24 -> 107998.98 | I25: =I8-I24 -> 143250.55 | J25: =J8-J24 -> 137107.03 | ... N25: =N8-N24 -> 151642.27 | O25: =SUM(C25:N25) -> 1487391.1 | P25: =IFERROR(O25/O6,0) -> 0.74263951
A26: Margen Bruto Operativo (%) | C26: =IFERROR(C25/C6,0) -> 0.74775334 | D26: =IFERROR(D25/D6,0) -> 0.78717575 | E26: =IFERROR(E25/E6,0) -> 0.81639442 | F26: =IFERROR(F25/F6,0) -> 0.70922137 | G26: =IFERROR(G25/G6,0) -> 0.71106002 | H26: =IFERROR(H25/H6,0) -> 0.7261783 | I26: =IFERROR(I25/I6,0) -> 0.77241188 | J26: =IFERROR(J25/J6,0) -> 0.77143406 | ... O26: =IFERROR(O25/O6,0) -> 0.74263951
A28: C. COSTO DE PERSONAL
A29: Sueldos y Salarios | B29: 6211100 | C29: 28638 | D29: 24200 | E29: 24769.22 | F29: 23860 | G29: 23320 | H29: 24302.84 | I29: 24478.67 | J29: 22073.33 | K29: 22726.23 | L29: 22740 | M29: 20823.33 | N29: 18203.34 | O29: =SUM(C29:N29) -> 280134.96 | P29: =IFERROR(O29/O6,0) -> 0.13986859
A30: Asignación Familiar | B30: 6211101 | C30: 339 | D30: 226 | E30: 339 | F30: 452 | G30: 452 | H30: 452 | I30: 452 | J30: 452 | K30: 565 | L30: 452 | M30: 565 | N30: 565 | O30: =SUM(C30:N30) -> 5311 | P30: =IFERROR(O30/O6,0) -> 0.0026517293
A31: Remuneración Vacacional | B31: 6211103 | C31: 0 | D31: 0 | E31: 0 | F31: 0 | G31: 0 | H31: 0 | I31: 0 | J31: 1000 | K31: 166.67 | L31: 0 | M31: 0 | N31: 533.33 | O31: =SUM(C31:N31) -> 1700 | P31: =IFERROR(O31/O6,0) -> 0.00084879303
A32: Rem. por Feriados | B32: 6211104 | C32: 0 | D32: 0 | E32: 0 | F32: 2986.67 | G32: 1493.33 | H32: 3053.33 | I32: 4413.33 | J32: 2366.67 | K32: 0 | L32: 1186.67 | M32: 1453.33 | N32: 4063.33 | O32: =SUM(C32:N32) -> 21016.66 | P32: =IFERROR(O32/O6,0) -> 0.010493409
A33: Movilidad Personal | B33: 6211105 | C33: 100 | D33: 100 | E33: 100 | F33: 100 | G33: 100 | H33: 100 | I33: 100 | J33: 100 | K33: 100 | L33: 100 | M33: 100 | N33: 100 | O33: =SUM(C33:N33) -> 1200 | P33: =IFERROR(O33/O6,0) -> 0.00059914802
A34: Rem. Vacacional Trunca | B34: 6211106 | C34: 0 | D34: 0 | E34: 0 | F34: 379.17 | G34: 563.33 | H34: 150 | I34: 488.38 | J34: 2470 | K34: 2507.46 | L34: 646.67 | M34: 4055 | N34: 26.67 | O34: =SUM(C34:N34) -> 11286.68 | P34: =IFERROR(O34/O6,0) -> 0.0056353267
A35: Horas Extras | B35: 6212101 | C35: 2052.13 | D35: 559.31 | E35: 559.31 | F35: 559.31 | G35: 681.53 | H35: 559.31 | I35: 559.31 | J35: 559.31 | K35: 559.31 | L35: 511.81 | M35: 559.31 | N35: 620.06 | O35: =SUM(C35:N35) -> 8340.01 | P35: =IFERROR(O35/O6,0) -> 0.0041640838
A36: Gratificaciones | B36: 6214100 | C36: 818.84 | D36: 8728.04 | E36: 0 | F36: 483.33 | G36: 1000 | H36: 200 | I36: 15426.12 | J36: 1700 | K36: 2149.25 | L36: 1866.67 | M36: 5500 | N36: 14565.21 | O36: =SUM(C36:N36) -> 52437.46 | P36: =IFERROR(O36/O6,0) -> 0.0261815
A37: Bonificación Extraordinaria | B37: 6214101 | C37: 73.7 | D37: 785.52 | E37: 0 | F37: 43.5 | G37: 90 | H37: 18 | I37: 1388.36 | J37: 153 | K37: 193.43 | L37: 168 | M37: 495 | N37: 1310.87 | O37: =SUM(C37:N37) -> 4719.38 | P37: =IFERROR(O37/O6,0) -> 0.0023563393
A38: Bonificación Regular | B38: 6214103 | C38: 1859.88 | D38: 1615.48 | E38: 1693 | F38: 2400 | G38: 1400 | H38: 0 | I38: 680 | J38: 3090 | K38: 1580 | L38: 760 | M38: 700 | N38: 280 | O38: =SUM(C38:N38) -> 16058.36 | P38: =IFERROR(O38/O6,0) -> 0.0080177789
A39: Vacaciones | B39: 6215100 | C39: 4354.54 | D39: 20244.97 | E39: 0 | F39: 0 | G39: 0 | H39: 0 | I39: 0 | J39: 0 | K39: 0 | L39: 0 | M39: 0 | N39: 0 | O39: =SUM(C39:N39) -> 24599.51 | P39: =IFERROR(O39/O6,0) -> 0.01228229
A40: Otras Remuneraciones | B40: 6221100 | C40: 0 | D40: 1000 | E40: 0 | F40: 0 | G40: 0 | H40: 2020 | I40: 1580 | J40: 2260 | K40: 1583.33 | L40: 2736.67 | M40: 2010 | N40: 1406.67 | O40: =SUM(C40:N40) -> 14596.67 | P40: =IFERROR(O40/O6,0) -> 0.0072879717
A41: Capacitación | B41: 6241100 | C41: 0 | D41: 0 | E41: 0 | F41: 0 | G41: 0 | H41: 0 | I41: 0 | J41: 500 | K41: 0 | L41: 0 | M41: 0 | N41: 0 | O41: =SUM(C41:N41) -> 500 | P41: =IFERROR(O41/O6,0) -> 0.00024964501
A42: Atención al Personal | B42: 6251100 | C42: 1920 | D42: 115.81 | E42: 389.78 | F42: 237.12 | G42: 852.61 | H42: 1087.99 | I42: 1453.49 | J42: 2313.06 | K42: 554.67 | L42: 317.11 | M42: 368.04 | N42: 2519.19 | O42: =SUM(C42:N42) -> 12128.87 | P42: =IFERROR(O42/O6,0) -> 0.0060558237
A43: EsSalud | B43: 6271100 | C43: 3351.92 | D43: 4335.83 | E43: 2538.65 | F43: 2764.98 | G43: 2588.12 | H43: 2868.23 | I43: 2796.45 | J43: 2971.65 | K43: 2656.69 | L43: 2438.74 | M43: 2257.62 | N43: 2384.56 | O43: =SUM(C43:N43) -> 33953.44 | P43: =IFERROR(O43/O6,0) -> 0.016952614
A44: SCTR | B44: 6273100 | C44: 100 | D44: 0 | E44: 0 | F44: 4055.51 | G44: 0 | H44: 0 | I44: 0 | J44: 0 | K44: 0 | L44: 0 | M44: 0 | N44: 0 | O44: =SUM(C44:N44) -> 4155.51 | P44: =IFERROR(O44/O6,0) -> 0.0020748047
A45: CTS | B45: 6291100 | C45: 1455.51 | D45: 5507.03 | E45: 0 | F45: 379.17 | G45: 163.33 | H45: 120 | I45: 429.2 | J45: 1892.77 | K45: 1982.77 | L45: 9959.82 | M45: 1880.82 | N45: 1430.71 | O45: =SUM(C45:N45) -> 25201.13 | P45: =IFERROR(O45/O6,0) -> 0.012582673
A46: TOTAL COSTO DE PERSONAL | C46: =C29+C30+C31+C32+C33+C34+C35+C36+C37+C38+C39+C40+C41+C42+C43+C44+C45 -> 45063.52 | D46: =D29+D30+D31+D32+D33+D34+D35+D36+D37+D38+D39+D40+D41+D42+D43+D44+D45 -> 67417.99 | E46: =E29+E30+E31+E32+E33+E34+E35+E36+E37+E38+E39+E40+E41+E42+E43+E44+E45 -> 30388.96 | F46: =F29+F30+F31+F32+F33+F34+F35+F36+F37+F38+F39+F40+F41+F42+F43+F44+F45 -> 38700.76 | G46: =G29+G30+G31+G32+G33+G34+G35+G36+G37+G38+G39+G40+G41+G42+G43+G44+G45 -> 32704.25 | H46: =H29+H30+H31+H32+H33+H34+H35+H36+H37+H38+H39+H40+H41+H42+H43+H44+H45 -> 34931.7 | I46: =I29+I30+I31+I32+I33+I34+I35+I36+I37+I38+I39+I40+I41+I42+I43+I44+I45 -> 54245.31 | J46: =J29+J30+J31+J32+J33+J34+J35+J36+J37+J38+J39+J40+J41+J42+J43+J44+J45 -> 43901.79 | ... N46: =N29+N30+N31+N32+N33+N34+N35+N36+N37+N38+N39+N40+N41+N42+N43+N44+N45 -> 48008.94 | O46: =SUM(C46:N46) -> 517339.64 | P46: =IFERROR(O46/O6,0) -> 0.25830252
A47: ★ UTILIDAD DESPUÉS DE PERSONAL (UBO − C) | C47: =C25-C46 -> 98781.82 | D47: =D25-D46 -> 101271.71 | E47: =E25-E46 -> 99453.87 | F47: =F25-F46 -> 76473.18 | G47: =G25-G46 -> 71576.79 | H47: =H25-H46 -> 73067.28 | I47: =I25-I46 -> 89005.24 | J47: =J25-J46 -> 93205.24 | ... N47: =N25-N46 -> 103633.33 | O47: =SUM(C47:N47) -> 970051.41 | P47: =IFERROR(O47/O6,0) -> 0.48433699
A48: Margen después de Personal (%) | C48: =IFERROR(C47/C6,0) -> 0.51349898 | D48: =IFERROR(D47/D6,0) -> 0.47257559 | E48: =IFERROR(E47/E6,0) -> 0.62532205 | F48: =IFERROR(F47/F6,0) -> 0.47090872 | G48: =IFERROR(G47/G6,0) -> 0.4880599 | H48: =IFERROR(H47/H6,0) -> 0.49129976 | I48: =IFERROR(I47/I6,0) -> 0.47991931 | J48: =IFERROR(J47/J6,0) -> 0.52442021 | ... O48: =IFERROR(O47/O6,0) -> 0.48433699
A50: D. GASTOS COMERCIALES
A51: Publicidad y Marketing | B51: 6371100 | C51: 0 | D51: 0 | E51: 0 | F51: 0 | G51: 0 | H51: 0 | I51: 0 | J51: 0 | K51: 0 | L51: 0 | M51: 6464.02 | N51: 3000 | O51: =SUM(C51:N51) -> 9464.02 | P51: =IFERROR(O51/O6,0) -> 0.0047252907
A52: Servicios de Diseño Gráfico | B52: 6381105 | C52: 1700 | D52: 1700 | E52: 1700 | F52: 1700 | G52: 1700 | H52: 1729.9 | I52: 1700 | J52: 0 | K52: 0 | L52: 0 | M52: 0 | N52: 0 | O52: =SUM(C52:N52) -> 11929.9 | P52: =IFERROR(O52/O6,0) -> 0.00595648
A53: Creación de Contenido Digital | B53: 6381108 | C53: 29.9 | D53: 0 | E53: 59.8 | F53: 59.8 | G53: 0 | H53: 0 | I53: 0 | J53: 0 | K53: 0 | L53: 1416.7 | M53: 0 | N53: 0 | O53: =SUM(C53:N53) -> 1566.2 | P53: =IFERROR(O53/O6,0) -> 0.00078198803
A54: Servicio de Eventos | B54: 6381110 | C54: 3008.55 | D54: 2128.44 | E54: 742.54 | F54: 3201.54 | G54: 2485.34 | H54: 3310.44 | I54: 4338.92 | J54: 2433.95 | K54: 1315.69 | L54: 2090.02 | M54: 2816.98 | N54: 4495.9 | O54: =SUM(C54:N54) -> 32368.31 | P54: =IFERROR(O54/O6,0) -> 0.016161174
A55: Comisión sobre Ventas | B55: 6381114 | C55: 1896.54 | D55: 772.04 | E55: 0 | F55: 73.33 | G55: 357.05 | H55: 205.99 | I55: 85.8 | J55: 412.15 | K55: 197.3 | L55: 3561.78 | M55: 24.15 | N55: 0 | O55: =SUM(C55:N55) -> 7586.13 | P55: =IFERROR(O55/O6,0) -> 0.003787679
A56: Comisión Tarjeta de Crédito | B56: 6561110 | C56: 4317.61 | D56: 4346.69 | E56: 630.3 | F56: 2347.24 | G56: 2411.1 | H56: 3317.14 | I56: 3569.3 | J56: 5484.3 | K56: 3187.57 | L56: 4678.59 | M56: 3185 | N56: 5309.99 | O56: =SUM(C56:N56) -> 42784.83 | P56: =IFERROR(O56/O6,0) -> 0.021362039
A57: TOTAL GASTOS COMERCIALES | C57: =C51+C52+C53+C54+C55+C56 -> 10952.6 | D57: =D51+D52+D53+D54+D55+D56 -> 8947.17 | E57: =E51+E52+E53+E54+E55+E56 -> 3132.64 | F57: =F51+F52+F53+F54+F55+F56 -> 7381.91 | G57: =G51+G52+G53+G54+G55+G56 -> 6953.49 | H57: =H51+H52+H53+H54+H55+H56 -> 8563.47 | I57: =I51+I52+I53+I54+I55+I56 -> 9694.02 | J57: =J51+J52+J53+J54+J55+J56 -> 8330.4 | ... N57: =N51+N52+N53+N54+N55+N56 -> 12805.89 | O57: =SUM(C57:N57) -> 105699.39 | P57: =IFERROR(O57/O6,0) -> 0.052774651
A58: ★ UTILIDAD COMERCIAL (UDP − D) | C58: =C47-C57 -> 87829.22 | D58: =D47-D57 -> 92324.54 | E58: =E47-E57 -> 96321.23 | F58: =F47-F57 -> 69091.27 | G58: =G47-G57 -> 64623.3 | H58: =H47-H57 -> 64503.81 | I58: =I47-I57 -> 79311.22 | J58: =J47-J57 -> 84874.84 | ... N58: =N47-N57 -> 90827.44 | O58: =SUM(C58:N58) -> 864352.02 | P58: =IFERROR(O58/O6,0) -> 0.43156234
A60: E. GASTOS ADMINISTRATIVOS
A61: Asesoría Administrativa | B61: 6321100 | C61: 2300 | D61: 0 | E61: 0 | F61: 240 | G61: 0 | H61: 0 | I61: 0 | J61: 0 | K61: 0 | L61: 0 | M61: 0 | N61: 0 | O61: =SUM(C61:N61) -> 2540 | P61: =IFERROR(O61/O6,0) -> 0.0012681966
A62: Asesoría Legal / Tributaria | B62: 6322100 | C62: 1500 | D62: 0 | E62: 1500 | F62: 0 | G62: 0 | H62: 0 | I62: 0 | J62: 0 | K62: 750 | L62: 0 | M62: 0 | N62: 1200 | O62: =SUM(C62:N62) -> 4950 | P62: =IFERROR(O62/O6,0) -> 0.0024714856
A63: Auditoría y Contabilidad | B63: 6323100 | C63: 2000 | D63: 2000 | E63: 0 | F63: 0 | G63: 4000 | H63: 4000 | I63: 2000 | J63: 2000 | K63: 2000 | L63: 2000 | M63: 2000 | N63: 2000 | O63: =SUM(C63:N63) -> 24000 | P63: =IFERROR(O63/O6,0) -> 0.01198296
A64: Otros Servicios de Asesoría | B64: 6329100 | C64: 500 | D64: 3250 | E64: 0 | F64: 0 | G64: 0 | H64: 200 | I64: 0 | J64: 0 | K64: 0 | L64: 0 | M64: 1500 | N64: 2100 | O64: =SUM(C64:N64) -> 7550 | P64: =IFERROR(O64/O6,0) -> 0.0037696396
A65: Gastos Bancarios | B65: 6391100 | C65: 395.43 | D65: 178.6 | E65: 133.69 | F65: 528.93 | G65: 347.05 | H65: 200.22 | I65: 179.24 | J65: 178.24 | K65: 183.69 | L65: 177.49 | M65: 177.74 | N65: 219.5 | O65: =SUM(C65:N65) -> 2899.82 | P65: =IFERROR(O65/O6,0) -> 0.0014478512
A66: ITF | B66: 6412100 | C66: 17.17 | D66: 22.63 | E66: 4.7 | F66: 14.78 | G66: 13.33 | H66: 14.39 | I66: 15.22 | J66: 16.35 | K66: 15.05 | L66: 13.2 | M66: 11.65 | N66: 20.75 | O66: =SUM(C66:N66) -> 179.22 | P66: =IFERROR(O66/O6,0) -> 8.9482757e-05
A67: Arbitrios Municipales | B67: 6432100 | C67: 0 | D67: 0 | E67: 0 | F67: 0 | G67: 0 | H67: 0 | I67: 0 | J67: 0 | K67: 0 | L67: 12837.24 | M67: 0 | N67: 0 | O67: =SUM(C67:N67) -> 12837.24 | P67: =IFERROR(O67/O6,0) -> 0.0064095058
A68: Otros Tributos | B68: 6443100 | C68: 0 | D68: 0 | E68: 0 | F68: 0 | G68: 0 | H68: 0 | I68: 0 | J68: 0 | K68: 0 | L68: 0 | M68: 0 | N68: 0 | O68: =SUM(C68:N68) -> 0 | P68: =IFERROR(O68/O6,0) -> 0
A69: Intereses Deuda Tributaria | B69: 6451100 | C69: 4 | D69: 0 | E69: 0 | F69: 0 | G69: 0 | H69: 0 | I69: 0 | J69: 0 | K69: 0 | L69: 0 | M69: 0 | N69: 0 | O69: =SUM(C69:N69) -> 4 | P69: =IFERROR(O69/O6,0) -> 1.9971601e-06
A70: Seguros | B70: 6511100 | C70: 0 | D70: 0 | E70: 0 | F70: 0 | G70: 0 | H70: 4808.84 | I70: 0 | J70: 0 | K70: 0 | L70: 0 | M70: 0 | N70: 0 | O70: =SUM(C70:N70) -> 4808.84 | P70: =IFERROR(O70/O6,0) -> 0.0024010058
A71: Suscripciones | B71: 6531100 | C71: 0 | D71: 0 | E71: 0 | F71: 0 | G71: 691.25 | H71: 160 | I71: 5123 | J71: 179.4 | K71: 177 | L71: 0 | M71: 177.57 | N71: 177.21 | O71: =SUM(C71:N71) -> 6685.43 | P71: =IFERROR(O71/O6,0) -> 0.0033379685
A72: Licencias | B72: 6541100 | C72: 0 | D72: 0 | E72: 0 | F72: 0 | G72: 160 | H72: 181.6 | I72: 177.45 | J72: 0 | K72: 0 | L72: 173.4 | M72: 0 | N72: 0 | O72: =SUM(C72:N72) -> 692.45 | P72: =IFERROR(O72/O6,0) -> 0.00034573337
A73: Útiles de Oficina | B73: 6561102 | C73: 689.76 | D73: 355.24 | E73: 44.83 | F73: 66.27 | G73: 154.66 | H73: 38.14 | I73: 58.05 | J73: 363.18 | K73: 591.05 | L73: 25 | M73: 163.56 | N73: 8.48 | O73: =SUM(C73:N73) -> 2558.22 | P73: =IFERROR(O73/O6,0) -> 0.0012772937
A74: Gastos Registro Público | B74: 6561105 | C74: 32.1 | D74: 0 | E74: 185.34 | F74: 0 | G74: 0 | H74: 32.1 | I74: -1 | J74: 0 | K74: 0 | L74: 0 | M74: 0 | N74: 0 | O74: =SUM(C74:N74) -> 248.54 | P74: =IFERROR(O74/O6,0) -> 0.00012409354
A75: Activo Menor | B75: 6561107 | C75: 188.5 | D75: 694.79 | E75: 0 | F75: 183.85 | G75: 0 | H75: 0 | I75: 635.59 | J75: 155.34 | K75: 0 | L75: 0 | M75: 0 | N75: 0 | O75: =SUM(C75:N75) -> 1858.07 | P75: =IFERROR(O75/O6,0) -> 0.00092771581
A76: Gastos Notariales | B76: 6561108 | C76: 0 | D76: 0 | E76: 52.12 | F76: 0 | G76: 0 | H76: 101.69 | I76: 556.36 | J76: 0 | K76: 0 | L76: 0 | M76: 0 | N76: 0 | O76: =SUM(C76:N76) -> 710.17 | P76: =IFERROR(O76/O6,0) -> 0.00035458079
A77: Impresiones y Copias | B77: 6561109 | C77: 157.63 | D77: 0 | E77: 0 | F77: 74.58 | G77: 64.41 | H77: 356.77 | I77: 0 | J77: 0 | K77: 0 | L77: 0 | M77: 0 | N77: 0 | O77: =SUM(C77:N77) -> 653.39 | P77: =IFERROR(O77/O6,0) -> 0.00032623111
A78: Peaje | B78: 6591103 | C78: 0 | D78: 0 | E78: 0 | F78: 0 | G78: 11.18 | H78: 0 | I78: 0 | J78: 0 | K78: 0 | L78: 0 | M78: 0 | N78: 0 | O78: =SUM(C78:N78) -> 11.18 | P78: =IFERROR(O78/O6,0) -> 5.5820624e-06
A79: Gastos de Representación | B79: 6591106 | C79: 0 | D79: 0 | E79: 0 | F79: 0 | G79: 0 | H79: 0 | I79: 0 | J79: 0 | K79: 0 | L79: 0 | M79: 0 | N79: 550.33 | O79: =SUM(C79:N79) -> 550.33 | P79: =IFERROR(O79/O6,0) -> 0.00027477428
A80: Otros Gastos Diversos | B80: 6591107 | C80: 0 | D80: 0 | E80: 0 | F80: 0 | G80: 0 | H80: 2192.44 | I80: 0 | J80: 0 | K80: 0 | L80: 0 | M80: 0 | N80: 0 | O80: =SUM(C80:N80) -> 2192.44 | P80: =IFERROR(O80/O6,0) -> 0.0010946634
A81: TOTAL GASTOS ADMINISTRATIVOS | C81: =C61+C62+C63+C64+C65+C66+C67+C68+C69+C70+C71+C72+C73+C74+C75+C76+C77+C78+C79+C80 -> 7784.59 | D81: =D61+D62+D63+D64+D65+D66+D67+D68+D69+D70+D71+D72+D73+D74+D75+D76+D77+D78+D79+D80 -> 6501.26 | E81: =E61+E62+E63+E64+E65+E66+E67+E68+E69+E70+E71+E72+E73+E74+E75+E76+E77+E78+E79+E80 -> 1920.68 | F81: =F61+F62+F63+F64+F65+F66+F67+F68+F69+F70+F71+F72+F73+F74+F75+F76+F77+F78+F79+F80 -> 1108.41 | G81: =G61+G62+G63+G64+G65+G66+G67+G68+G69+G70+G71+G72+G73+G74+G75+G76+G77+G78+G79+G80 -> 5441.88 | H81: =H61+H62+H63+H64+H65+H66+H67+H68+H69+H70+H71+H72+H73+H74+H75+H76+H77+H78+H79+H80 -> 12286.19 | I81: =I61+I62+I63+I64+I65+I66+I67+I68+I69+I70+I71+I72+I73+I74+I75+I76+I77+I78+I79+I80 -> 8743.91 | J81: =J61+J62+J63+J64+J65+J66+J67+J68+J69+J70+J71+J72+J73+J74+J75+J76+J77+J78+J79+J80 -> 2892.51 | ... N81: =N61+N62+N63+N64+N65+N66+N67+N68+N69+N70+N71+N72+N73+N74+N75+N76+N77+N78+N79+N80 -> 6276.27 | O81: =SUM(C81:N81) -> 75929.34 | P81: =IFERROR(O81/O6,0) -> 0.037910762
A83: F. GASTOS FIJOS / ESTRUCTURA
A84: Alquiler Local (Estructura) | B84: 6352102 | C84: 50842.5 | D84: 49882.5 | E84: 49477.5 | F84: 50449.5 | G84: 49896 | H84: 48586.5 | I84: 48168 | J84: 48505.5 | K84: 48019.5 | L84: 46534.5 | M84: 46737 | N84: 46443.5 | O84: =SUM(C84:N84) -> 583542.5 | P84: =IFERROR(O84/O6,0) -> 0.29135695
A85: Alquiler de Equipos | B85: 6356100 | C85: 156.78 | D85: 0 | E85: 0 | F85: 313.56 | G85: 0 | H85: 313.56 | I85: 0 | J85: 156.78 | K85: 156.78 | L85: 156.78 | M85: 156.78 | N85: 156.78 | O85: =SUM(C85:N85) -> 1567.8 | P85: =IFERROR(O85/O6,0) -> 0.00078278689
A86: Internet y Conectividad | B86: 6365100 | C86: 184.75 | D86: 184.75 | E86: 0 | F86: 0 | G86: 123.42 | H86: 88.98 | I86: 88.98 | J86: 88.98 | K86: 0 | L86: 88.98 | M86: 88.98 | N86: 172.88 | O86: =SUM(C86:N86) -> 1110.7 | P86: =IFERROR(O86/O6,0) -> 0.00055456142
A87: Servicio de Monitoreo/CCTV | B87: 6381100 | C87: 1159.16 | D87: 0 | E87: 0 | F87: 18 | G87: 0 | H87: 402.54 | I87: 0 | J87: 1420 | K87: 0 | L87: 0 | M87: 0 | N87: 0 | O87: =SUM(C87:N87) -> 2999.7 | P87: =IFERROR(O87/O6,0) -> 0.0014977203
A88: Servicios Informáticos | B88: 6381101 | C88: 0 | D88: 0 | E88: 800 | F88: 0 | G88: 0 | H88: 0 | I88: 0 | J88: 0 | K88: 0 | L88: 0 | M88: 250 | N88: 0 | O88: =SUM(C88:N88) -> 1050 | P88: =IFERROR(O88/O6,0) -> 0.00052425452
A89: Servicio Operador | B89: 6381102 | C89: 1200 | D89: 0 | E89: 0 | F89: 0 | G89: 0 | H89: 0 | I89: 0 | J89: 0 | K89: 0 | L89: 0 | M89: 0 | N89: 0 | O89: =SUM(C89:N89) -> 1200 | P89: =IFERROR(O89/O6,0) -> 0.00059914802
A90: Servicios de Sistemas | B90: 6381103 | C90: 0 | D90: 0 | E90: 0 | F90: 0 | G90: 0 | H90: 6500 | I90: 0 | J90: 0 | K90: 0 | L90: 0 | M90: 0 | N90: 0 | O90: =SUM(C90:N90) -> 6500 | P90: =IFERROR(O90/O6,0) -> 0.0032453851
A91: Soporte Técnico | B91: 6381104 | C91: 0 | D91: 0 | E91: 0 | F91: 0 | G91: 0 | H91: 0 | I91: 0 | J91: 0 | K91: 0 | L91: 0 | M91: 0 | N91: 149.46 | O91: =SUM(C91:N91) -> 149.46 | P91: =IFERROR(O91/O6,0) -> 7.4623886e-05
A92: Servicio de Seguridad | B92: 6381111 | C92: 1040 | D92: 2606.67 | E92: 1700 | F92: 3557.44 | G92: 1813 | H92: 1946.66 | I92: 2040 | J92: 906.4 | K92: 0 | L92: 0 | M92: 0 | N92: 400 | O92: =SUM(C92:N92) -> 16010.17 | P92: =IFERROR(O92/O6,0) -> 0.0079937181
A93: Servicios Varios | B93: 6381112 | C93: 100 | D93: 0 | E93: 0 | F93: 0 | G93: 0 | H93: 0 | I93: 0 | J93: 234 | K93: 0 | L93: 375 | M93: 0 | N93: 360 | O93: =SUM(C93:N93) -> 1069 | P93: =IFERROR(O93/O6,0) -> 0.00053374103
A94: Transporte de Carga | B94: 6311100 | C94: 0 | D94: 0 | E94: 0 | F94: 0 | G94: 0 | H94: 0 | I94: 15 | J94: 20 | K94: 0 | L94: 0 | M94: 470 | N94: 0 | O94: =SUM(C94:N94) -> 505 | P94: =IFERROR(O94/O6,0) -> 0.00025214146
A95: Transporte de Pasajeros | B95: 6311200 | C95: 0 | D95: 0 | E95: 0 | F95: 0 | G95: 0 | H95: 423.73 | I95: 0 | J95: 0 | K95: 0 | L95: 145 | M95: 185 | N95: 165 | O95: =SUM(C95:N95) -> 918.73 | P95: =IFERROR(O95/O6,0) -> 0.00045871272
A96: Planilla Movilidad | B96: 6311201 | C96: 238.2 | D96: 371.94 | E96: 530.4 | F96: 252.5 | G96: 328.5 | H96: 228 | I96: 650 | J96: 524.09 | K96: 141.4 | L96: 108.2 | M96: 481.3 | N96: 0 | O96: =SUM(C96:N96) -> 3854.53 | P96: =IFERROR(O96/O6,0) -> 0.0019245284
A97: Alojamiento | B97: 6313100 | C97: 0 | D97: 0 | E97: 0 | F97: 0 | G97: 0 | H97: 127.27 | I97: 0 | J97: 0 | K97: 0 | L97: 0 | M97: 0 | N97: 0 | O97: =SUM(C97:N97) -> 127.27 | P97: =IFERROR(O97/O6,0) -> 6.3544641e-05
A98: Alimentación Operativa | B98: 6314100 | C98: 208 | D98: 128 | E98: 106.5 | F98: 0 | G98: 355.2 | H98: 122.7 | I98: 425.34 | J98: 116.23 | K98: 683.26 | L98: 0 | M98: 0 | N98: 0 | O98: =SUM(C98:N98) -> 2145.23 | P98: =IFERROR(O98/O6,0) -> 0.0010710919
A99: TOTAL GASTOS FIJOS / ESTRUCTURA | C99: =C84+C85+C86+C87+C88+C89+C90+C91+C92+C93+C94+C95+C96+C97+C98 -> 55129.39 | D99: =D84+D85+D86+D87+D88+D89+D90+D91+D92+D93+D94+D95+D96+D97+D98 -> 53173.86 | E99: =E84+E85+E86+E87+E88+E89+E90+E91+E92+E93+E94+E95+E96+E97+E98 -> 52614.4 | F99: =F84+F85+F86+F87+F88+F89+F90+F91+F92+F93+F94+F95+F96+F97+F98 -> 54591 | G99: =G84+G85+G86+G87+G88+G89+G90+G91+G92+G93+G94+G95+G96+G97+G98 -> 52516.12 | H99: =H84+H85+H86+H87+H88+H89+H90+H91+H92+H93+H94+H95+H96+H97+H98 -> 58739.94 | I99: =I84+I85+I86+I87+I88+I89+I90+I91+I92+I93+I94+I95+I96+I97+I98 -> 51387.32 | J99: =J84+J85+J86+J87+J88+J89+J90+J91+J92+J93+J94+J95+J96+J97+J98 -> 51971.98 | ... N99: =N84+N85+N86+N87+N88+N89+N90+N91+N92+N93+N94+N95+N96+N97+N98 -> 47847.62 | O99: =SUM(C99:N99) -> 622750.09 | P99: =IFERROR(O99/O6,0) -> 0.3109329
A101: ★★ EBITDA (UC − E − F) | C101: =C58-C81-C99 -> 24915.24 | D101: =D58-D81-D99 -> 32649.42 | E101: =E58-E81-E99 -> 41786.15 | F101: =F58-F81-F99 -> 13391.86 | G101: =G58-G81-G99 -> 6665.3 | H101: =H58-H81-H99 -> -6522.32 | I101: =I58-I81-I99 -> 19179.99 | J101: =J58-J81-J99 -> 30010.35 | ... N101: =N58-N81-N99 -> 36703.55 | O101: =SUM(C101:N101) -> 165672.59 | P101: =IFERROR(O101/O6,0) -> 0.082718671
A102: Margen EBITDA (%) | C102: =IFERROR(C101/C6,0) -> 0.12951726 | D102: =IFERROR(D101/D6,0) -> 0.15235567 | E102: =IFERROR(E101/E6,0) -> 0.26273287 | F102: =IFERROR(F101/F6,0) -> 0.082464777 | G102: =IFERROR(G101/G6,0) -> 0.04544861 | H102: =IFERROR(H101/H6,0) -> -0.043855667 | I102: =IFERROR(I101/I6,0) -> 0.10341916 | J102: =IFERROR(J101/J6,0) -> 0.16885353 | ... O102: =IFERROR(O101/O6,0) -> 0.082718671
A103: EBITDA Acumulado YTD | C103: =C101 -> 24915.24 | D103: =C103+D101 -> 57564.66 | E103: =D103+E101 -> 99350.81 | F103: =E103+F101 -> 112742.67 | G103: =F103+G101 -> 119407.97 | H103: =G103+H101 -> 112885.65 | I103: =H103+I101 -> 132065.64 | J103: =I103+J101 -> 162075.99 | K103: =J103+K101 -> 149678.75 | ... N103: =M103+N101 -> 165672.59 | O103: =O101 -> 165672.59
A105: G. DEPRECIACIÓN Y AMORTIZACIÓN
A106: Dep. Prop. Inv. Edificaciones | B106: 6811100 | C106: 1231.26 | D106: 1231.26 | E106: 0 | F106: 0 | G106: 0 | H106: 0 | I106: 0 | J106: 0 | K106: 0 | L106: 0 | M106: 0 | N106: 0 | O106: =SUM(C106:N106) -> 2462.52 | P106: =IFERROR(O106/O6,0) -> 0.0012295117
A107: Dep. Maquinaria | B107: 6841200 | C107: 135.95 | D107: 135.95 | E107: 0 | F107: 0 | G107: 0 | H107: 0 | I107: 0 | J107: 0 | K107: 0 | L107: 111.02 | M107: 111.02 | N107: 111.02 | O107: =SUM(C107:N107) -> 604.96 | P107: =IFERROR(O107/O6,0) -> 0.00030205049
A108: Dep. Muebles y Enseres | B108: 6841400 | C108: 199.89 | D108: 199.89 | E108: 0 | F108: 0 | G108: 0 | H108: 0 | I108: 0 | J108: 0 | K108: 0 | L108: 93.82 | M108: 93.82 | N108: 93.82 | O108: =SUM(C108:N108) -> 681.24 | P108: =IFERROR(O108/O6,0) -> 0.00034013633
...

Sheet Dashboard
A1: PERU ON ICE S.A.C. — DASHBOARD FINANCIERO 2025
A2: Análisis Visual | Ingresos | EBITDA | Márgenes | Ocupación | Costos por Hora
A4: INGRESOS 2025 | E4: EBITDA 2025 | I4: MARGEN EBITDA | M4: CHILLER | Q4: RESULTADO NETO
A5: S/ 2.00M | E5: S/ 165.7K | I5: 8.3% | M5: 26% ING. | Q5: S/ 134.7K
A8: Mes | B8: Ingresos (S/) | C8: EBITDA (S/) | D8: Costo Op. Hielo | E8: Personal | F8: % Margen EBITDA
A9: ENE | B9: ='P&L Gerencial'!C6 -> 192370.04 | C9: ='P&L Gerencial'!C101 -> 24915.24 | D9: ='P&L Gerencial'!C24 -> 48524.7 | E9: ='P&L Gerencial'!C46 -> 45063.52 | F9: =IFERROR('P&L Gerencial'!C101/'P&L Gerencial'!C6,0) -> 0.12951726
A10: FEB | B10: ='P&L Gerencial'!D6 -> 214297.38 | C10: ='P&L Gerencial'!D101 -> 32649.42 | D10: ='P&L Gerencial'!D24 -> 45607.68 | E10: ='P&L Gerencial'!D46 -> 67417.99 | F10: =IFERROR('P&L Gerencial'!D101/'P&L Gerencial'!D6,0) -> 0.15235567
A11: MAR | B11: ='P&L Gerencial'!E6 -> 159044.24 | C11: ='P&L Gerencial'!E101 -> 41786.15 | D11: ='P&L Gerencial'!E24 -> 29201.41 | E11: ='P&L Gerencial'!E46 -> 30388.96 | F11: =IFERROR('P&L Gerencial'!E101/'P&L Gerencial'!E6,0) -> 0.26273287
A12: ABR | B12: ='P&L Gerencial'!F6 -> 162394.91 | C12: ='P&L Gerencial'!F101 -> 13391.86 | D12: ='P&L Gerencial'!F24 -> 47220.97 | E12: ='P&L Gerencial'!F46 -> 38700.76 | F12: =IFERROR('P&L Gerencial'!F101/'P&L Gerencial'!F6,0) -> 0.082464777
A13: MAY | B13: ='P&L Gerencial'!G6 -> 146655.75 | C13: ='P&L Gerencial'!G101 -> 6665.3 | D13: ='P&L Gerencial'!G24 -> 42374.71 | E13: ='P&L Gerencial'!G46 -> 32704.25 | F13: =IFERROR('P&L Gerencial'!G101/'P&L Gerencial'!G6,0) -> 0.04544861
A14: JUN | B14: ='P&L Gerencial'!H6 -> 148722.4 | C14: ='P&L Gerencial'!H101 -> -6522.32 | D14: ='P&L Gerencial'!H24 -> 40723.42 | E14: ='P&L Gerencial'!H46 -> 34931.7 | F14: =IFERROR('P&L Gerencial'!H101/'P&L Gerencial'!H6,0) -> -0.043855667
A15: JUL | B15: ='P&L Gerencial'!I6 -> 185458.76 | C15: ='P&L Gerencial'!I101 -> 19179.99 | D15: ='P&L Gerencial'!I24 -> 42208.21 | E15: ='P&L Gerencial'!I46 -> 54245.31 | F15: =IFERROR('P&L Gerencial'!I101/'P&L Gerencial'!I6,0) -> 0.10341916
A16: AGO | B16: ='P&L Gerencial'!J6 -> 177730.07 | C16: ='P&L Gerencial'!J101 -> 30010.35 | D16: ='P&L Gerencial'!J24 -> 40623.04 | E16: ='P&L Gerencial'!J46 -> 43901.79 | F16: =IFERROR('P&L Gerencial'!J101/'P&L Gerencial'!J6,0) -> 0.16885353
A17: SET | B17: ='P&L Gerencial'!K6 -> 139427.16 | C17: ='P&L Gerencial'!K101 -> -12397.24 | D17: ='P&L Gerencial'!K24 -> 57081.3 | E17: ='P&L Gerencial'!K46 -> 37324.81 | F17: =IFERROR('P&L Gerencial'!K101/'P&L Gerencial'!K6,0) -> -0.088915531
A18: OCT | B18: ='P&L Gerencial'!L6 -> 144036.01 | C18: ='P&L Gerencial'!L101 -> -13120.41 | D18: ='P&L Gerencial'!L24 -> 38890.38 | E18: ='P&L Gerencial'!L46 -> 43884.16 | F18: =IFERROR('P&L Gerencial'!L101/'P&L Gerencial'!L6,0) -> -0.091091179
A19: NOV | B19: ='P&L Gerencial'!M6 -> 140103.32 | C19: ='P&L Gerencial'!M101 -> -7589.3 | D19: ='P&L Gerencial'!M24 -> 42035.44 | E19: ='P&L Gerencial'!M46 -> 40767.45 | F19: =IFERROR('P&L Gerencial'!M101/'P&L Gerencial'!M6,0) -> -0.054169309
A20: DIC | B20: ='P&L Gerencial'!N6 -> 192603.92 | C20: ='P&L Gerencial'!N101 -> 36703.55 | D20: ='P&L Gerencial'!N24 -> 40961.65 | E20: ='P&L Gerencial'!N46 -> 48008.94 | F20: =IFERROR('P&L Gerencial'!N101/'P&L Gerencial'!N6,0) -> 0.19056492
C22: ENE | D22: FEB | E22: MAR | F22: ABR | G22: MAY | H22: JUN | I22: JUL | J22: AGO | K22: SET | L22: OCT | M22: NOV | N22: DIC
A23: % Ocupación de Pista | C23: ='Indicadores Operativos'!B27 -> 0.21145238 | D23: ='Indicadores Operativos'!C27 -> 0.25993306 | E23: ='Indicadores Operativos'!D27 -> 0.17393982 | F23: ='Indicadores Operativos'!E27 -> 0.18563494 | G23: ='Indicadores Operativos'!F27 -> 0.15861796 | H23: ='Indicadores Operativos'!G27 -> 0.16914206 | I23: ='Indicadores Operativos'!H27 -> 0.20490392 | J23: ='Indicadores Operativos'!I27 -> 0.19130246 | ... N23: ='Indicadores Operativos'!M27 -> 0.2151747
A24: Ingreso por Hora Disponible (S/) | C24: ='Indicadores Operativos'!B39 -> 642.30397 | D24: ='Indicadores Operativos'!C39 -> 789.59978 | E24: ='Indicadores Operativos'!D39 -> 528.38618 | F24: ='Indicadores Operativos'!E39 -> 563.87122 | G24: ='Indicadores Operativos'!F39 -> 481.7863 | H24: ='Indicadores Operativos'!G39 -> 513.72159 | I24: ='Indicadores Operativos'!H39 -> 622.34483 | J24: ='Indicadores Operativos'!I39 -> 581.00709 | ... N24: ='Indicadores Operativos'!M39 -> 653.55928
A25: Costo Total por Hora Disponible (S/) | C25: ='Indicadores Operativos'!B38 -> 559.11452 | D25: ='Indicadores Operativos'!C38 -> 669.29978 | E25: ='Indicadores Operativos'!D38 -> 389.56176 | F25: ='Indicadores Operativos'!E38 -> 517.3717 | G25: ='Indicadores Operativos'!F38 -> 459.88978 | H25: ='Indicadores Operativos'!G38 -> 536.25119 | I25: ='Indicadores Operativos'!H38 -> 557.98245 | J25: ='Indicadores Operativos'!I38 -> 482.90199 | ... N25: ='Indicadores Operativos'!M38 -> 529.01381
A26: Margen S/ | C26: =+C24-C25 -> 83.189449 | D26: =+D24-D25 -> 120.3 | E26: =+E24-E25 -> 138.82442 | F26: =+F24-F25 -> 46.499514 | G26: =+G24-G25 -> 21.896518 | H26: =+H24-H25 -> -22.529603 | I26: =+I24-I25 -> 64.362383 | J26: =+J24-J25 -> 98.1051 | ... N26: =+N24-N25 -> 124.54547
A27: Margen % | C27: =+C25/C24*100 -> 87.048274 | D27: =+D25/D24*100 -> 84.764433 | E27: =+E25/E24*100 -> 73.726713 | F27: =+F25/F24*100 -> 91.753522 | G27: =+G25/G24*100 -> 95.455139 | H27: =+H25/H24*100 -> 104.38557 | I27: =+I25/I24*100 -> 89.658084 | J27: =+J25/J24*100 -> 83.114647 | ... N27: =+N25/N24*100 -> 80.943508

Sheet Comparativo vs PSTO
A1: PERU ON ICE — COMPARATIVO GERENCIAL: P&L 2026 REAL vs PRESUPUESTO 2026 (SIN IGV)
A2: Ppto 2026 = Proyectado ENE-DIC
A3: ▌ PARTE 1 — RESUMEN ANUAL
A4: CONCEPTO | B4: REAL 2026 (S/) | C4: PL 2025 (S/) | D4: PPTO 2026 (S/) | E4: VAR. (S/) | F4: VAR. (%) | G4: % REV 2025 | H4: % REV 2026 | I4: TENDENCIA
A5: A. INGRESOS
A6: Ingresos por Servicios de Pista | B6: ='P&L Gerencial'!O6 -> 2002844 | C6: ='P&L Gerencial'!O6 -> 2002844 | D6: ='Datos 2026'!O4 -> 2114576.3 | E6: =D6-B6 -> 111732.34 | F6: =IFERROR((D6-B6)/ABS(B6),0) -> 0.055786842 | G6: =IFERROR(B6/'P&L Gerencial'!O6,0) -> 1 | H6: =IFERROR(D6/2114576.3,0) -> 1 | I6: ▲ Mayor gasto
A8: B. COSTOS OPERATIVOS DEL HIELO
A9: Energía Eléctrica | B9: ='P&L Gerencial'!O11 -> 238552.34 | C9: ='P&L Gerencial'!O11 -> 238552.34 | D9: ='Datos 2026'!O38 -> 244281.07 | E9: =D9-B9 -> 5728.73 | F9: =IFERROR((D9-B9)/ABS(B9),0) -> 0.024014562 | G9: =IFERROR(B9/'P&L Gerencial'!O6,0) -> 0.1191068 | H9: =IFERROR(D9/2114576.3,0) -> 0.11552247 | I9: ▲ Mayor gasto
A10: Alquiler Chiller (Refrigeración) | B10: ='P&L Gerencial'!O12 -> 209000 | C10: ='P&L Gerencial'!O12 -> 209000 | D10: ='Datos 2026'!O35 -> 209000 | E10: =D10-B10 -> 0 | F10: =IFERROR((D10-B10)/ABS(B10),0) -> 0 | G10: =IFERROR(B10/'P&L Gerencial'!O6,0) -> 0.10435161 | H10: =IFERROR(D10/2114576.3,0) -> 0.098837767 | I10: ══
A11: Agua | B11: ='P&L Gerencial'!O13 -> 8174.44 | C11: ='P&L Gerencial'!O13 -> 8174.44 | D11: ='Datos 2026'!O39 -> 8355.47 | E11: =D11-B11 -> 181.03 | F11: =IFERROR((D11-B11)/ABS(B11),0) -> 0.02214586 | G11: =IFERROR(B11/'P&L Gerencial'!O6,0) -> 0.0040814163 | H11: =IFERROR(D11/2114576.3,0) -> 0.0039513684 | I11: ▲ Mayor gasto
A12: Mantenimiento Local | B12: ='P&L Gerencial'!O14 -> 22303.78 | C12: ='P&L Gerencial'!O14 -> 22303.78 | D12: ='Datos 2026'!O33 -> 23413.97 | E12: =D12-B12 -> 1110.19 | F12: =IFERROR((D12-B12)/ABS(B12),0) -> 0.049775868 | G12: =IFERROR(B12/'P&L Gerencial'!O6,0) -> 0.011136055 | H12: =IFERROR(D12/2114576.3,0) -> 0.011072653 | I12: ▲ Mayor gasto
A13: Otros costos operativos | B13: ='P&L Gerencial'!O16+'P&L Gerencial'!O17+'P&L Gerencial'!O18+'P&L Gerencial'!O19+'P&L Gerencial'!O20+'P&L Gerencial'!O21+'P&L Gerencial'!O22+'P&L Gerencial'!O23 -> 33722.35 | C13: ='P&L Gerencial'!O16+'P&L Gerencial'!O17+'P&L Gerencial'!O18+'P&L Gerencial'!O19+'P&L Gerencial'!O20+'P&L Gerencial'!O21+'P&L Gerencial'!O22+'P&L Gerencial'!O23 -> 33722.35 | D13: ='Datos 2026'!O53+'Datos 2026'!O54+'Datos 2026'!O64+'Datos 2026'!O66+'Datos 2026'!O67+'Datos 2026'!O69+'Datos 2026'!O75+'Datos 2026'!O76 -> 35032.41 | E13: =D13-B13 -> 1310.06 | F13: =IFERROR((D13-B13)/ABS(B13),0) -> 0.03884842 | G13: =IFERROR(B13/'P&L Gerencial'!O6,0) -> 0.016837233 | H13: =IFERROR(D13/2114576.3,0) -> 0.016567106 | I13: ▲ Mayor gasto
A14: TOTAL Costos Op. Hielo | B14: ='P&L Gerencial'!O24 -> 515452.91 | C14: ='P&L Gerencial'!O24 -> 515452.91 | D14: =SUM(D9:D13) -> 520082.92 | E14: =D14-C14 -> 4630.01 | F14: =IFERROR((D14-C14)/ABS(C14),0) -> 0.0089824112 | G14: =IFERROR(C14/'P&L Gerencial'!O6,0) -> 0.25736049 | H14: =IFERROR(D14/2114576.32,0) -> 0.24595136 | I14: ▲ Mayor gasto
A15: ★ UTILIDAD BRUTA OPERATIVA | B15: ='P&L Gerencial'!O25 -> 1487391.1 | C15: ='P&L Gerencial'!O25 -> 1487391.1 | D15: =+D6-D14 -> 1594493.4 | E15: =D15-C15 -> 107102.33 | F15: =IFERROR((D15-C15)/ABS(C15),0) -> 0.07200684 | G15: =IFERROR(C15/'P&L Gerencial'!O6,0) -> 0.74263951 | H15: =IFERROR(D15/2114576.32,0) -> 0.75404863 | I15: ▲ Mejora
A17: C. COSTO DE PERSONAL
A18: Sueldos y Salarios | B18: ='P&L Gerencial'!O29 -> 280134.96 | C18: ='P&L Gerencial'!O29 -> 280134.96 | D18: ='Datos 2026'!O7 -> 291499.81 | E18: =D18-B18 -> 11364.85 | F18: =IFERROR((D18-B18)/ABS(B18),0) -> 0.040569196 | G18: =IFERROR(B18/'P&L Gerencial'!O6,0) -> 0.13986859 | H18: =IFERROR(D18/2114576.3,0) -> 0.13785259 | I18: ▲ Mayor gasto
A19: Gratificaciones + CTS + EsSalud | B19: ='P&L Gerencial'!O36+'P&L Gerencial'!O45+'P&L Gerencial'!O43 -> 111592.03 | C19: ='P&L Gerencial'!O36+'P&L Gerencial'!O45+'P&L Gerencial'!O43 -> 111592.03 | D19: ='Datos 2026'!O14+'Datos 2026'!O23+'Datos 2026'!O21 -> 114739.18 | E19: =D19-B19 -> 3147.15 | F19: =IFERROR((D19-B19)/ABS(B19),0) -> 0.028202283 | G19: =IFERROR(B19/'P&L Gerencial'!O6,0) -> 0.055716787 | H19: =IFERROR(D19/2114576.3,0) -> 0.054261073 | I19: ▲ Mayor gasto
A20: Otras remuneraciones y cargas | B20: ='P&L Gerencial'!O30+'P&L Gerencial'!O31+'P&L Gerencial'!O32+'P&L Gerencial'!O33+'P&L Gerencial'!O34+'P&L Gerencial'!O35+'P&L Gerencial'!O37+'P&L Gerencial'!O38+'P&L Gerencial'!O39+'P&L Gerencial'!O40+'P&L Gerencial'!O41+'P&L Gerencial'!O42+'P&L Gerencial'!O44 -> 125612.65 | C20: ='P&L Gerencial'!O30+'P&L Gerencial'!O31+'P&L Gerencial'!O32+'P&L Gerencial'!O33+'P&L Gerencial'!O34+'P&L Gerencial'!O35+'P&L Gerencial'!O37+'P&L Gerencial'!O38+'P&L Gerencial'!O39+'P&L Gerencial'!O40+'P&L Gerencial'!O41+'P&L Gerencial'!O42+'P&L Gerencial'!O44 -> 125612.65 | D20: ='Datos 2026'!O8+'Datos 2026'!O9+'Datos 2026'!O10+'Datos 2026'!O11+'Datos 2026'!O12+'Datos 2026'!O13+'Datos 2026'!O15+'Datos 2026'!O16+'Datos 2026'!O17+'Datos 2026'!O18+'Datos 2026'!O19+'Datos 2026'!O20+'Datos 2026'!O22 -> 126960.03 | E20: =D20-B20 -> 1347.38 | F20: =IFERROR((D20-B20)/ABS(B20),0) -> 0.010726467 | G20: =IFERROR(B20/'P&L Gerencial'!O6,0) -> 0.062717142 | H20: =IFERROR(D20/2114576.3,0) -> 0.060040411 | I20: ▲ Mayor gasto
A21: TOTAL Personal | B21: ='P&L Gerencial'!O46 -> 517339.64 | C21: ='P&L Gerencial'!O46 -> 517339.64 | D21: =SUM(D18:D20) -> 533199.02 | E21: =D21-C21 -> 15859.38 | F21: =IFERROR((D21-C21)/ABS(C21),0) -> 0.030655644 | G21: =IFERROR(C21/'P&L Gerencial'!O6,0) -> 0.25830252 | H21: =IFERROR(D21/2114576.32,0) -> 0.25215407 | I21: ▲ Mayor gasto
A23: D. GASTOS COMERCIALES
A24: Comisión Tarjeta de Crédito | B24: ='P&L Gerencial'!O56 -> 42784.83 | C24: ='P&L Gerencial'!O56 -> 42784.83 | D24: ='Datos 2026'!O73 -> 44490.87 | E24: =D24-B24 -> 1706.04 | F24: =IFERROR((D24-B24)/ABS(B24),0) -> 0.039874881 | G24: =IFERROR(B24/'P&L Gerencial'!O6,0) -> 0.021362039 | H24: =IFERROR(D24/2114576.3,0) -> 0.021040087 | I24: ▲ Mayor gasto
A25: Publicidad y Marketing | B25: ='P&L Gerencial'!O51+'P&L Gerencial'!O52+'P&L Gerencial'!O53 -> 22960.12 | C25: ='P&L Gerencial'!O51+'P&L Gerencial'!O52+'P&L Gerencial'!O53 -> 22960.12 | D25: ='Datos 2026'!O41+'Datos 2026'!O47+'Datos 2026'!O48 -> 25006.55 | E25: =D25-B25 -> 2046.43 | F25: =IFERROR((D25-B25)/ABS(B25),0) -> 0.089129761 | G25: =IFERROR(B25/'P&L Gerencial'!O6,0) -> 0.011463759 | H25: =IFERROR(D25/2114576.3,0) -> 0.011825797 | I25: ▲ Mayor gasto
A26: Comisión Ventas + Eventos | B26: ='P&L Gerencial'!O54+'P&L Gerencial'!O55 -> 39954.44 | C26: ='P&L Gerencial'!O54+'P&L Gerencial'!O55 -> 39954.44 | D26: ='Datos 2026'!O49+'Datos 2026'!O52 -> 41561.89 | E26: =D26-B26 -> 1607.45 | F26: =IFERROR((D26-B26)/ABS(B26),0) -> 0.040232074 | G26: =IFERROR(B26/'P&L Gerencial'!O6,0) -> 0.019948853 | H26: =IFERROR(D26/2114576.3,0) -> 0.019654949 | I26: ▲ Mayor gasto
A27: TOTAL Comercial | B27: ='P&L Gerencial'!O57 -> 105699.39 | C27: ='P&L Gerencial'!O57 -> 105699.39 | D27: =SUM(D24:D26) -> 111059.31 | E27: =D27-C27 -> 5359.92 | F27: =IFERROR((D27-C27)/ABS(C27),0) -> 0.050709091 | G27: =IFERROR(C27/'P&L Gerencial'!O6,0) -> 0.052774651 | H27: =IFERROR(D27/2114576.32,0) -> 0.052520833 | I27: ▲ Mayor gasto
A29: E. GASTOS ADMINISTRATIVOS
A30: Asesorías (Admin+Legal+Contab) | B30: ='P&L Gerencial'!O61+'P&L Gerencial'!O62+'P&L Gerencial'!O63+'P&L Gerencial'!O64 -> 39040 | C30: ='P&L Gerencial'!O61+'P&L Gerencial'!O62+'P&L Gerencial'!O63+'P&L Gerencial'!O64 -> 39040 | D30: ='Datos 2026'!O29+'Datos 2026'!O30+'Datos 2026'!O31+'Datos 2026'!O32 -> 39604.5 | E30: =D30-B30 -> 564.5 | F30: =IFERROR((D30-B30)/ABS(B30),0) -> 0.014459529 | G30: =IFERROR(B30/'P&L Gerencial'!O6,0) -> 0.019492282 | H30: =IFERROR(D30/2114576.3,0) -> 0.018729284 | I30: ▲ Mayor gasto
A31: Tributos y Seguros | B31: ='P&L Gerencial'!O67+'P&L Gerencial'!O70 -> 17646.08 | C31: ='P&L Gerencial'!O67+'P&L Gerencial'!O70 -> 17646.08 | D31: ='Datos 2026'!O57+'Datos 2026'!O60 -> 18271.64 | E31: =D31-B31 -> 625.56 | F31: =IFERROR((D31-B31)/ABS(B31),0) -> 0.035450366 | G31: =IFERROR(B31/'P&L Gerencial'!O6,0) -> 0.0088105116 | H31: =IFERROR(D31/2114576.3,0) -> 0.0086408043 | I31: ▲ Mayor gasto
A32: Otros administrativos | B32: ='P&L Gerencial'!O65+'P&L Gerencial'!O66+'P&L Gerencial'!O68+'P&L Gerencial'!O69+'P&L Gerencial'!O71+'P&L Gerencial'!O72+'P&L Gerencial'!O73+'P&L Gerencial'!O74+'P&L Gerencial'!O75+'P&L Gerencial'!O76+'P&L Gerencial'!O77+'P&L Gerencial'!O78+'P&L Gerencial'!O79+'P&L Gerencial'!O80 -> 19243.26 | C32: ='P&L Gerencial'!O65+'P&L Gerencial'!O66+'P&L Gerencial'!O68+'P&L Gerencial'!O69+'P&L Gerencial'!O71+'P&L Gerencial'!O72+'P&L Gerencial'!O73+'P&L Gerencial'!O74+'P&L Gerencial'!O75+'P&L Gerencial'!O76+'P&L Gerencial'!O77+'P&L Gerencial'!O78+'P&L Gerencial'!O79+'P&L Gerencial'!O80 -> 19243.26 | D32: ='Datos 2026'!O55+'Datos 2026'!O56+'Datos 2026'!O58+'Datos 2026'!O59+'Datos 2026'!O61+'Datos 2026'!O62+'Datos 2026'!O65+'Datos 2026'!O68+'Datos 2026'!O70+'Datos 2026'!O71+'Datos 2026'!O72+'Datos 2026'!O74+'Datos 2026'!O77+'Datos 2026'!O78 -> 19835.77 | E32: =D32-B32 -> 592.51 | F32: =IFERROR((D32-B32)/ABS(B32),0) -> 0.030790521 | G32: =IFERROR(B32/'P&L Gerencial'!O6,0) -> 0.0096079677 | H32: =IFERROR(D32/2114576.3,0) -> 0.0093804939 | I32: ▲ Mayor gasto
A33: TOTAL Administrativo | B33: ='P&L Gerencial'!O81 -> 75929.34 | C33: ='P&L Gerencial'!O81 -> 75929.34 | D33: =SUM(D30:D32) -> 77711.91 | E33: =D33-C33 -> 1782.57 | F33: =IFERROR((D33-C33)/ABS(C33),0) -> 0.023476696 | G33: =IFERROR(C33/'P&L Gerencial'!O6,0) -> 0.037910762 | H33: =IFERROR(D33/2114576.32,0) -> 0.036750582 | I33: ▲ Mayor gasto
A35: F. GASTOS FIJOS / ESTRUCTURA
A36: Alquiler Local | B36: ='P&L Gerencial'!O84 -> 583542.5 | C36: ='P&L Gerencial'!O84 -> 583542.5 | D36: ='Datos 2026'!O36 -> 593198.85 | E36: =D36-B36 -> 9656.35 | F36: =IFERROR((D36-B36)/ABS(B36),0) -> 0.016547809 | G36: =IFERROR(B36/'P&L Gerencial'!O6,0) -> 0.29135695 | H36: =IFERROR(D36/2114576.3,0) -> 0.28052847 | I36: ▲ Mayor gasto
A37: Servicio de Seguridad | B37: ='P&L Gerencial'!O92 -> 16010.17 | C37: ='P&L Gerencial'!O92 -> 16010.17 | D37: ='Datos 2026'!O50 -> 16628.34 | E37: =D37-B37 -> 618.17 | F37: =IFERROR((D37-B37)/ABS(B37),0) -> 0.038611083 | G37: =IFERROR(B37/'P&L Gerencial'!O6,0) -> 0.0079937181 | H37: =IFERROR(D37/2114576.3,0) -> 0.0078636746 | I37: ▲ Mayor gasto
A38: Otros servicios estructura | B38: ='P&L Gerencial'!O85+'P&L Gerencial'!O86+'P&L Gerencial'!O87+'P&L Gerencial'!O88+'P&L Gerencial'!O89+'P&L Gerencial'!O90+'P&L Gerencial'!O91+'P&L Gerencial'!O93+'P&L Gerencial'!O94+'P&L Gerencial'!O95+'P&L Gerencial'!O96+'P&L Gerencial'!O97+'P&L Gerencial'!O98 -> 23197.42 | C38: ='P&L Gerencial'!O85+'P&L Gerencial'!O86+'P&L Gerencial'!O87+'P&L Gerencial'!O88+'P&L Gerencial'!O89+'P&L Gerencial'!O90+'P&L Gerencial'!O91+'P&L Gerencial'!O93+'P&L Gerencial'!O94+'P&L Gerencial'!O95+'P&L Gerencial'!O96+'P&L Gerencial'!O97+'P&L Gerencial'!O98 -> 23197.42 | D38: ='Datos 2026'!O37+'Datos 2026'!O40+'Datos 2026'!O42+'Datos 2026'!O43+'Datos 2026'!O44+'Datos 2026'!O45+'Datos 2026'!O46+'Datos 2026'!O51+'Datos 2026'!O24+'Datos 2026'!O25+'Datos 2026'!O26+'Datos 2026'!O27+'Datos 2026'!O28 -> 23551.01 | E38: =D38-B38 -> 353.59 | F38: =IFERROR((D38-B38)/ABS(B38),0) -> 0.015242643 | G38: =IFERROR(B38/'P&L Gerencial'!O6,0) -> 0.01158224 | H38: =IFERROR(D38/2114576.3,0) -> 0.01113746 | I38: ▲ Mayor gasto
A39: TOTAL Estructura | B39: ='P&L Gerencial'!O99 -> 622750.09 | C39: ='P&L Gerencial'!O99 -> 622750.09 | D39: =D36+D37+D38 -> 633378.2 | E39: =D39-B39 -> 10628.11 | F39: =IFERROR((D39-B39)/ABS(B39),0) -> 0.017066413 | G39: =IFERROR(B39/'P&L Gerencial'!O6,0) -> 0.3109329 | H39: =IFERROR(D39/2114576.3,0) -> 0.2995296 | I39: ▲ Mayor gasto
A41: ★★ EBITDA | B41: ='P&L Gerencial'!O101 -> 165672.59 | C41: ='P&L Gerencial'!O101 -> 165672.59 | D41: =+D15-D21-D27-D33-D39 -> 239144.94 | E41: =D41-C41 -> 73472.35 | F41: =IFERROR((D41-C41)/ABS(C41),0) -> 0.44347921 | G41: =IFERROR(C41/'P&L Gerencial'!O6,0) -> 0.082718671 | H41: =IFERROR(D41/2114576.32,0) -> 0.11309355 | I41: ▲ Mejora
A42: Margen EBITDA (%) | B42: =IFERROR(B41/B6,0) -> 0.082718671 | C42: =IFERROR(C41/C6,0) -> 0.082718671 | D42: =IFERROR(D41/D6,0) -> 0.11309355 | E42: =IFERROR(D42-B42,0) -> 0.030374879 | F42: =IFERROR((D42-B42)/ABS(B42),0) -> 0.36720705 | G42: =IFERROR(C42/'P&L Gerencial'!O6,0) -> 4.1300607e-08 | H42: =IFERROR(D42/2114576.32,0) -> 5.3482841e-08 | I42: ▲ Mejora
A44: G. DEPRECIACIÓN
A45: TOTAL Depreciación | B45: ='P&L Gerencial'!O111 -> 7526.73 | C45: ='P&L Gerencial'!O111 -> 7526.73 | D45: ='Datos 2026'!O81+'Datos 2026'!O82+'Datos 2026'!O83+'Datos 2026'!O84+'Datos 2026'!O85 -> 7526.73 | E45: =D45-B45 -> 0 | F45: =IFERROR((D45-B45)/ABS(B45),0) -> -2.4167061e-16 | G45: =IFERROR(B45/'P&L Gerencial'!O6,0) -> 0.0037580212 | H45: =IFERROR(D45/2114576.3,0) -> 0.0035594507 | I45: ══
A46: EBIT — Utilidad Operativa | B46: ='P&L Gerencial'!O112 -> 158145.86 | C46: ='P&L Gerencial'!O112 -> 158145.86 | D46: =+D41-D45 -> 231618.21 | E46: =D46-C46 -> 73472.35 | F46: =IFERROR((D46-C46)/ABS(C46),0) -> 0.46458598 | G46: =IFERROR(C46/'P&L Gerencial'!O6,0) -> 0.07896065 | H46: =IFERROR(D46/2114576.32,0) -> 0.1095341 | I46: ▲ Mayor gasto
A48: H. RESULTADO FINANCIERO NETO
A49: Resultado Financiero Neto | B49: ='P&L Gerencial'!O118+'P&L Gerencial'!O119-'P&L Gerencial'!O115-'P&L Gerencial'!O116 -> -23455.02 | C49: ='P&L Gerencial'!O118+'P&L Gerencial'!O119-'P&L Gerencial'!O115-'P&L Gerencial'!O116 -> -23455.02 | D49: ='Datos 2026'!O5+'Datos 2026'!O6-'Datos 2026'!O79+'Datos 2026'!O80 -> -23429.24 | E49: =D49-B49 -> 25.78 | F49: =IFERROR((D49-B49)/ABS(B49),0) -> 0.001099125 | G49: =IFERROR(B49/'P&L Gerencial'!O6,0) -> -0.011710857 | H49: =IFERROR(D49/2114576.3,0) -> -0.011079874 | I49: ══
A51: ★★★ UTILIDAD NETA | B51: ='P&L Gerencial'!O123 -> 134690.84 | C51: ='P&L Gerencial'!O123 -> 134690.84 | D51: =+D46+D49 -> 208188.97 | E51: =D51-C51 -> 73498.13 | F51: =IFERROR((D51-C51)/ABS(C51),0) -> 0.54568024 | G51: =IFERROR(C51/'P&L Gerencial'!O6,0) -> 0.067249792 | H51: =IFERROR(D51/2114576.32,0) -> 0.098454224 | I51: ▲ Mejora
A52: Margen Neto (%) | B52: =IFERROR(B51/B6,0) -> 0.067249792 | C52: =IFERROR(C51/C6,0) -> 0.067249792 | D52: =IFERROR(D51/D6,0) -> 0.098454225 | E52: =IFERROR(D52-B52,0) -> 0.031204432 | F52: =IFERROR((D52-B52)/ABS(B52),0) -> 0.46400786 | G52: =IFERROR(C52/'P&L Gerencial'!O6,0) -> 3.357715e-08 | H52: =IFERROR(D52/2114576.32,0) -> 4.6559788e-08 | I52: ▲ Mejora
A54: ▌ PARTE 2 — EVOLUCIÓN MENSUAL 2025 (P&L Real)
A55: MÉTRICA | B55: ENE | C55: FEB | D55: MAR | E55: ABR | F55: MAY | G55: JUN | H55: JUL | I55: AGO | J55: SET | K55: OCT | L55: NOV | M55: DIC | N55: TOTAL
A56: Ingresos (S/) | B56: ='P&L Gerencial'!C6 -> 192370.04 | C56: ='P&L Gerencial'!D6 -> 214297.38 | D56: ='P&L Gerencial'!E6 -> 159044.24 | E56: ='P&L Gerencial'!F6 -> 162394.91 | F56: ='P&L Gerencial'!G6 -> 146655.75 | G56: ='P&L Gerencial'!H6 -> 148722.4 | H56: ='P&L Gerencial'!I6 -> 185458.76 | I56: ='P&L Gerencial'!J6 -> 177730.07 | ... M56: ='P&L Gerencial'!N6 -> 192603.92 | N56: =SUM(B56:M56) -> 2002844
A57: EBITDA (S/) | B57: ='P&L Gerencial'!C101 -> 24915.24 | C57: ='P&L Gerencial'!D101 -> 32649.42 | D57: ='P&L Gerencial'!E101 -> 41786.15 | E57: ='P&L Gerencial'!F101 -> 13391.86 | F57: ='P&L Gerencial'!G101 -> 6665.3 | G57: ='P&L Gerencial'!H101 -> -6522.32 | H57: ='P&L Gerencial'!I101 -> 19179.99 | I57: ='P&L Gerencial'!J101 -> 30010.35 | ... M57: ='P&L Gerencial'!N101 -> 36703.55 | N57: =SUM(B57:M57) -> 165672.59
A58: % Margen EBITDA | B58: =IFERROR('P&L Gerencial'!C101/'P&L Gerencial'!C6,0) -> 0.12951726 | C58: =IFERROR('P&L Gerencial'!D101/'P&L Gerencial'!D6,0) -> 0.15235567 | D58: =IFERROR('P&L Gerencial'!E101/'P&L Gerencial'!E6,0) -> 0.26273287 | E58: =IFERROR('P&L Gerencial'!F101/'P&L Gerencial'!F6,0) -> 0.082464777 | F58: =IFERROR('P&L Gerencial'!G101/'P&L Gerencial'!G6,0) -> 0.04544861 | G58: =IFERROR('P&L Gerencial'!H101/'P&L Gerencial'!H6,0) -> -0.043855667 | H58: =IFERROR('P&L Gerencial'!I101/'P&L Gerencial'!I6,0) -> 0.10341916 | I58: =IFERROR('P&L Gerencial'!J101/'P&L Gerencial'!J6,0) -> 0.16885353 | ... M58: =IFERROR('P&L Gerencial'!N101/'P&L Gerencial'!N6,0) -> 0.19056492 | N58: =AVERAGE(B58:M58) -> 0.071443759
A59: Costos Op. Hielo (S/) | B59: ='P&L Gerencial'!C24 -> 48524.7 | C59: ='P&L Gerencial'!D24 -> 45607.68 | D59: ='P&L Gerencial'!E24 -> 29201.41 | E59: ='P&L Gerencial'!F24 -> 47220.97 | F59: ='P&L Gerencial'!G24 -> 42374.71 | G59: ='P&L Gerencial'!H24 -> 40723.42 | H59: ='P&L Gerencial'!I24 -> 42208.21 | I59: ='P&L Gerencial'!J24 -> 40623.04 | ... M59: ='P&L Gerencial'!N24 -> 40961.65 | N59: =SUM(B59:M59) -> 515452.91
A60: % Energía/Ingresos | B60: =IFERROR('P&L Gerencial'!C11/'P&L Gerencial'!C6,0) -> 0.1182851 | C60: =IFERROR('P&L Gerencial'!D11/'P&L Gerencial'!D6,0) -> 0.11591257 | D60: =IFERROR('P&L Gerencial'!E11/'P&L Gerencial'!E6,0) -> 0.14589947 | E60: =IFERROR('P&L Gerencial'!F11/'P&L Gerencial'!F6,0) -> 0.14028753 | F60: =IFERROR('P&L Gerencial'!G11/'P&L Gerencial'!G6,0) -> 0.13917415 | G60: =IFERROR('P&L Gerencial'!H11/'P&L Gerencial'!H6,0) -> 0.12623465 | H60: =IFERROR('P&L Gerencial'!I11/'P&L Gerencial'!I6,0) -> 0.095581411 | I60: =IFERROR('P&L Gerencial'!J11/'P&L Gerencial'!J6,0) -> 0.096301993 | ... M60: =IFERROR('P&L Gerencial'!N11/'P&L Gerencial'!N6,0) -> 0.098584286 | N60: =AVERAGE(B60:M60) -> 0.12037014
A61: Personal (S/) | B61: ='P&L Gerencial'!C46 -> 45063.52 | C61: ='P&L Gerencial'!D46 -> 67417.99 | D61: ='P&L Gerencial'!E46 -> 30388.96 | E61: ='P&L Gerencial'!F46 -> 38700.76 | F61: ='P&L Gerencial'!G46 -> 32704.25 | G61: ='P&L Gerencial'!H46 -> 34931.7 | H61: ='P&L Gerencial'!I46 -> 54245.31 | I61: ='P&L Gerencial'!J46 -> 43901.79 | ... M61: ='P&L Gerencial'!N46 -> 48008.94 | N61: =SUM(B61:M61) -> 517339.64
A62: Alquiler Local (S/) | B62: ='P&L Gerencial'!C84 -> 50842.5 | C62: ='P&L Gerencial'!D84 -> 49882.5 | D62: ='P&L Gerencial'!E84 -> 49477.5 | E62: ='P&L Gerencial'!F84 -> 50449.5 | F62: ='P&L Gerencial'!G84 -> 49896 | G62: ='P&L Gerencial'!H84 -> 48586.5 | H62: ='P&L Gerencial'!I84 -> 48168 | I62: ='P&L Gerencial'!J84 -> 48505.5 | ... M62: ='P&L Gerencial'!N84 -> 46443.5 | N62: =SUM(B62:M62) -> 583542.5
A63: Utilidad Neta (S/) | B63: ='P&L Gerencial'!C123 -> 15058.68 | C63: ='P&L Gerencial'!D123 -> 27637.13 | D63: ='P&L Gerencial'!E123 -> 41778.88 | E63: ='P&L Gerencial'!F123 -> 12383.87 | F63: ='P&L Gerencial'!G123 -> 5587.03 | G63: ='P&L Gerencial'!H123 -> -7763.69 | H63: ='P&L Gerencial'!I123 -> 17363.25 | I63: ='P&L Gerencial'!J123 -> 28877.29 | ... M63: ='P&L Gerencial'!N123 -> 31888.88 | N63: =SUM(B63:M63) -> 134690.84

Sheet Indicadores Operativos
A1: PERU ON ICE — DRIVERS OPERATIVOS Y MODELO DE INGRESOS
A2: Aforo: 40 pers. pista / 98 local | Chiller: 24/7
A4: MÉTRICA / PARÁMETRO | B4: ENE | C4: FEB | D4: MAR | E4: ABR | F4: MAY | G4: JUN | H4: JUL | I4: AGO | J4: SET | K4: OCT | L4: NOV | M4: DIC | N4: TOTAL / PROM. | O4: TOTAL / PROM.
A5: 1. ESTRUCTURA DE TARIFAS Y MEZCLA DE PRODUCTOS
A6: PRODUCTO/SERVICIO | B6: PRECIO | C6: DESCRIPCIÓN | D6: SEGMENTO
A7: Entrada 25 minutos | B7: S/ 35 | C7: Tarifa estándar público general
A8: Entrada 55 minutos | B8: S/ 60 | C8: Tarifa extendida público general
A9: Membresía Coach | B9: S/ 150/mes | C9: Acceso 5AM-10PM ilimitado
A10: Membresía Deportistas | B10: S/ 350/mes | C10: Clases L/M 4:40-9:30 PM | M/J 4:30-6 PM + Free Practice 5-9 AM
A11: Salón Off-Ice | B11: S/ 30 | C11: Uso del salón sin acceso a pista
A13: 2. TICKET PROMEDIO REAL Y VISITAS MENSUALES
A14: Ticket Promedio Real (S/) — Calibrado Feb 2025 | B14: 41.51 | C14: 41.51 | D14: 41.51 | E14: 41.51 | F14: 41.51 | G14: 41.51 | H14: 41.51 | I14: 41.51 | J14: 41.51 | K14: 41.51 | L14: 41.51 | M14: 41.51 | O14: =SUM(B14:N14) -> 498.12
A15: Visitas al Mes (real/estimado) | B15: 4634 | C15: 5162 | D15: 3831 | E15: 3912 | F15: 3533 | G15: 3583 | H15: 4468 | I15: 4282 | J15: 3359 | K15: 3470 | L15: 3375 | M15: 4640 | O15: =SUM(B15:N15) -> 48249
C16: ↑ Confirmado Feb 2025
A17: Ingresos Calculados (Visitas × Ticket) | B17: =B15*B14 -> 192357.34 | C17: =C15*C14 -> 214274.62 | D17: =D15*D14 -> 159024.81 | E17: =E15*E14 -> 162387.12 | F17: =F15*F14 -> 146654.83 | G17: =G15*G14 -> 148730.33 | H17: =H15*H14 -> 185466.68 | I17: =I15*I14 -> 177745.82 | ... M17: =M15*M14 -> 192606.4 | O17: =SUM(B17:N17) -> 2002816
A18: Ingresos Reales P&L (vínculo) | B18: ='P&L Gerencial'!C6 -> 192370.04 | C18: ='P&L Gerencial'!D6 -> 214297.38 | D18: ='P&L Gerencial'!E6 -> 159044.24 | E18: ='P&L Gerencial'!F6 -> 162394.91 | F18: ='P&L Gerencial'!G6 -> 146655.75 | G18: ='P&L Gerencial'!H6 -> 148722.4 | H18: ='P&L Gerencial'!I6 -> 185458.76 | I18: ='P&L Gerencial'!J6 -> 177730.07 | ... M18: ='P&L Gerencial'!N6 -> 192603.92 | O18: =SUM(B18:N18) -> 2002844
A20: 3. CAPACIDAD DE PISTA Y ANÁLISIS DE OCUPACIÓN
A21: HORARIO: Atención al público 10AM-10PM (12 hrs/día) | Clases L/M: 4:40PM-9:30PM (pista cerrada a público) | Clases M/J: 4:30PM-6PM (pista cerrada a público) | Mantenimiento: 1PM y 6PM (~15 min c/u) | Chiller: 24/7 | Aforo pista: 40 personas
A22: Horas Disponibles al Público (calculadas por calendario) | B22: 299.5 | C22: 271.4 | D22: 301 | E22: 288 | F22: 304.4 | G22: 289.5 | H22: 298 | I22: 305.9 | J22: 288 | K22: 299.5 | L22: 294.4 | M22: 294.7 | O22: =SUM(B22:N22) -> 3534.3
A23: Aforo Máximo Pista (personas simultáneas) | B23: 40 | C23: 40 | D23: 40 | E23: 40 | F23: 40 | G23: 40 | H23: 40 | I23: 40 | J23: 40 | K23: 40 | L23: 40 | M23: 40 | O23: =SUM(B23:N23) -> 480
A24: Duración Prom. Sesión (hrs) — calculada del mix Simulador: =(vol_25*(25/60)+vol_55*(55/60))/(vol_25+vol_55) | B24: =IFERROR((Simulador!B16*(25/60)+Simulador!B17*(55/60))/(Simulador!B16+Simulador!B17),25/60) -> 0.54665504 | C24: =IFERROR((Simulador!B16*(25/60)+Simulador!B17*(55/60))/(Simulador!B16+Simulador!B17),25/60) -> 0.54665504 | D24: =IFERROR((Simulador!B16*(25/60)+Simulador!B17*(55/60))/(Simulador!B16+Simulador!B17),25/60) -> 0.54665504 | E24: =IFERROR((Simulador!B16*(25/60)+Simulador!B17*(55/60))/(Simulador!B16+Simulador!B17),25/60) -> 0.54665504 | F24: =IFERROR((Simulador!B16*(25/60)+Simulador!B17*(55/60))/(Simulador!B16+Simulador!B17),25/60) -> 0.54665504 | G24: =IFERROR((Simulador!B16*(25/60)+Simulador!B17*(55/60))/(Simulador!B16+Simulador!B17),25/60) -> 0.54665504 | H24: =IFERROR((Simulador!B16*(25/60)+Simulador!B17*(55/60))/(Simulador!B16+Simulador!B17),25/60) -> 0.54665504 | I24: =IFERROR((Simulador!B16*(25/60)+Simulador!B17*(55/60))/(Simulador!B16+Simulador!B17),25/60) -> 0.54665504 | J24: =IFERROR((Simulador!B16*(25/60)+Simulador!B17*(55/60))/(Simulador!B16+Simulador!B17),25/60) -> 0.54665504 | K24: =IFERROR((Simulador!B16*(25/60)+Simulador!B17*(55/60))/(Simulador!B16+Simulador!B17),25/60) -> 0.54665504 | L24: =IFERROR((Simulador!B16*(25/60)+Simulador!B17*(55/60))/(Simulador!B16+Simulador!B17),25/60) -> 0.54665504 | M24: =IFERROR((Simulador!B16*(25/60)+Simulador!B17*(55/60))/(Simulador!B16+Simulador!B17),25/60) -> 0.54665504 | O24: =AVERAGE(B24:N24) -> 0.54665504
A25: Capacidad Máxima (person-horas / mes) | B25: =B22*B23 -> 11980 | C25: =C22*C23 -> 10856 | D25: =D22*D23 -> 12040 | E25: =E22*E23 -> 11520 | F25: =F22*F23 -> 12176 | G25: =G22*G23 -> 11580 | H25: =H22*H23 -> 11920 | I25: =I22*I23 -> 12236 | ... M25: =M22*M23 -> 11788 | O25: =SUM(B25:N25) -> 141372
A26: Person-Horas Vendidas (visitas × duración prom.) | B26: =B15*B24 -> 2533.1995 | C26: =C15*C24 -> 2821.8333 | D26: =D15*D24 -> 2094.2355 | E26: =E15*E24 -> 2138.5145 | F26: =F15*F24 -> 1931.3323 | G26: =G15*G24 -> 1958.665 | H26: =H15*H24 -> 2442.4547 | I26: =I15*I24 -> 2340.7769 | ... M26: =M15*M24 -> 2536.4794 | O26: =SUM(B26:N26) -> 26375.559
A27: ★ % Ocupación de Pista | B27: =IFERROR(B26/B25,0) -> 0.21145238 | C27: =IFERROR(C26/C25,0) -> 0.25993306 | D27: =IFERROR(D26/D25,0) -> 0.17393982 | E27: =IFERROR(E26/E25,0) -> 0.18563494 | F27: =IFERROR(F26/F25,0) -> 0.15861796 | G27: =IFERROR(G26/G25,0) -> 0.16914206 | H27: =IFERROR(H26/H25,0) -> 0.20490392 | I27: =IFERROR(I26/I25,0) -> 0.19130246 | ... M27: =IFERROR(M26/M25,0) -> 0.2151747 | O27: =AVERAGE(B27:N27) -> 0.18704204
A28: Personas Promedio Simultáneas en Pista | B28: =IFERROR(B26/B22,0) -> 8.4580951 | C28: =IFERROR(C26/C22,0) -> 10.397323 | D28: =IFERROR(D26/D22,0) -> 6.9575929 | E28: =IFERROR(E26/E22,0) -> 7.4253977 | F28: =IFERROR(F26/F22,0) -> 6.3447184 | G28: =IFERROR(G26/G22,0) -> 6.7656823 | H28: =IFERROR(H26/H22,0) -> 8.1961568 | I28: =IFERROR(I26/I22,0) -> 7.6520984 | ... M28: =IFERROR(M26/M22,0) -> 8.6069881 | O28: =AVERAGE(B28:N28) -> 7.4816816
A29: Visitas por Hora Disponible | B29: =IFERROR(B15/B22,0) -> 15.472454 | C29: =IFERROR(C15/C22,0) -> 19.019897 | D29: =IFERROR(D15/D22,0) -> 12.727575 | E29: =IFERROR(E15/E22,0) -> 13.583333 | F29: =IFERROR(F15/F22,0) -> 11.606439 | G29: =IFERROR(G15/G22,0) -> 12.376511 | H29: =IFERROR(H15/H22,0) -> 14.993289 | I29: =IFERROR(I15/I22,0) -> 13.998039 | ... M29: =IFERROR(M15/M22,0) -> 15.744825 | O29: =AVERAGE(B29:N29) -> 13.686294
A31: 4. ANÁLISIS DE INGRESO Y COSTO POR HORA — KPIs CLAVE
A32: Costos Operativos Hielo (del P&L) | B32: ='P&L Gerencial'!C24 -> 48524.7 | C32: ='P&L Gerencial'!D24 -> 45607.68 | D32: ='P&L Gerencial'!E24 -> 29201.41 | E32: ='P&L Gerencial'!F24 -> 47220.97 | F32: ='P&L Gerencial'!G24 -> 42374.71 | G32: ='P&L Gerencial'!H24 -> 40723.42 | H32: ='P&L Gerencial'!I24 -> 42208.21 | I32: ='P&L Gerencial'!J24 -> 40623.04 | ... M32: ='P&L Gerencial'!N24 -> 40961.65 | O32: =SUM(B32:N32) -> 515452.91
A33: Costo de Personal (del P&L) | B33: ='P&L Gerencial'!C46 -> 45063.52 | C33: ='P&L Gerencial'!D46 -> 67417.99 | D33: ='P&L Gerencial'!E46 -> 30388.96 | E33: ='P&L Gerencial'!F46 -> 38700.76 | F33: ='P&L Gerencial'!G46 -> 32704.25 | G33: ='P&L Gerencial'!H46 -> 34931.7 | H33: ='P&L Gerencial'!I46 -> 54245.31 | I33: ='P&L Gerencial'!J46 -> 43901.79 | ... M33: ='P&L Gerencial'!N46 -> 48008.94 | O33: =SUM(B33:N33) -> 517339.64
A34: Costos Totales Operativos (sin Deprec.) | B34: ='P&L Gerencial'!C24+'P&L Gerencial'!C46+'P&L Gerencial'!C57+'P&L Gerencial'!C81+'P&L Gerencial'!C99 -> 167454.8 | C34: ='P&L Gerencial'!D24+'P&L Gerencial'!D46+'P&L Gerencial'!D57+'P&L Gerencial'!D81+'P&L Gerencial'!D99 -> 181647.96 | D34: ='P&L Gerencial'!E24+'P&L Gerencial'!E46+'P&L Gerencial'!E57+'P&L Gerencial'!E81+'P&L Gerencial'!E99 -> 117258.09 | E34: ='P&L Gerencial'!F24+'P&L Gerencial'!F46+'P&L Gerencial'!F57+'P&L Gerencial'!F81+'P&L Gerencial'!F99 -> 149003.05 | F34: ='P&L Gerencial'!G24+'P&L Gerencial'!G46+'P&L Gerencial'!G57+'P&L Gerencial'!G81+'P&L Gerencial'!G99 -> 139990.45 | G34: ='P&L Gerencial'!H24+'P&L Gerencial'!H46+'P&L Gerencial'!H57+'P&L Gerencial'!H81+'P&L Gerencial'!H99 -> 155244.72 | H34: ='P&L Gerencial'!I24+'P&L Gerencial'!I46+'P&L Gerencial'!I57+'P&L Gerencial'!I81+'P&L Gerencial'!I99 -> 166278.77 | I34: ='P&L Gerencial'!J24+'P&L Gerencial'!J46+'P&L Gerencial'!J57+'P&L Gerencial'!J81+'P&L Gerencial'!J99 -> 147719.72 | ... M34: ='P&L Gerencial'!N24+'P&L Gerencial'!N46+'P&L Gerencial'!N57+'P&L Gerencial'!N81+'P&L Gerencial'!N99 -> 155900.37 | O34: =SUM(B34:N34) -> 1837171.4
A36: ⚡ Costo Operativo Hielo por Hora Disponible (S/) | B36: =IFERROR(B32/B22,0) -> 162.01903 | C36: =IFERROR(C32/C22,0) -> 168.04598 | D36: =IFERROR(D32/D22,0) -> 97.014651 | E36: =IFERROR(E32/E22,0) -> 163.9617 | F36: =IFERROR(F32/F22,0) -> 139.20733 | G36: =IFERROR(G32/G22,0) -> 140.66812 | H36: =IFERROR(H32/H22,0) -> 141.63829 | I36: =IFERROR(I32/I22,0) -> 132.79843 | ... M36: =IFERROR(M32/M22,0) -> 138.9944 | O36: =AVERAGE(B36:N36) -> 146.26511
A37: 👥 Costo de Personal por Hora Disponible (S/) | B37: =IFERROR(B33/B22,0) -> 150.4625 | C37: =IFERROR(C33/C22,0) -> 248.40822 | D37: =IFERROR(D33/D22,0) -> 100.96 | E37: =IFERROR(E33/E22,0) -> 134.37764 | F37: =IFERROR(F33/F22,0) -> 107.4384 | G37: =IFERROR(G33/G22,0) -> 120.66218 | H37: =IFERROR(H33/H22,0) -> 182.03124 | I37: =IFERROR(I33/I22,0) -> 143.5168 | ... M37: =IFERROR(M33/M22,0) -> 162.90784 | O37: =AVERAGE(B37:N37) -> 147.11383
A38: 💼 Costo Total por Hora Disponible (S/) | B38: =IFERROR(B34/B22,0) -> 559.11452 | C38: =IFERROR(C34/C22,0) -> 669.29978 | D38: =IFERROR(D34/D22,0) -> 389.56176 | E38: =IFERROR(E34/E22,0) -> 517.3717 | F38: =IFERROR(F34/F22,0) -> 459.88978 | G38: =IFERROR(G34/G22,0) -> 536.25119 | H38: =IFERROR(H34/H22,0) -> 557.98245 | I38: =IFERROR(I34/I22,0) -> 482.90199 | ... M38: =IFERROR(M34/M22,0) -> 529.01381 | O38: =AVERAGE(B38:N38) -> 521.24647
A39: 💰 Ingreso por Hora Disponible (S/) | B39: =IFERROR(B18/B22,0) -> 642.30397 | C39: =IFERROR(C18/C22,0) -> 789.59978 | D39: =IFERROR(D18/D22,0) -> 528.38618 | E39: =IFERROR(E18/E22,0) -> 563.87122 | F39: =IFERROR(F18/F22,0) -> 481.7863 | G39: =IFERROR(G18/G22,0) -> 513.72159 | H39: =IFERROR(H18/H22,0) -> 622.34483 | I39: =IFERROR(I18/I22,0) -> 581.00709 | ... M39: =IFERROR(M18/M22,0) -> 653.55928 | O39: =AVERAGE(B39:N39) -> 568.12653
A40: ★ MARGEN por Hora (S/) = Ingreso/hr − Costo/hr | B40: =B39-B38 -> 83.189449 | C40: =C39-C38 -> 120.3 | D40: =D39-D38 -> 138.82442 | E40: =E39-E38 -> 46.499514 | F40: =F39-F38 -> 21.896518 | G40: =G39-G38 -> -22.529603 | H40: =H39-H38 -> 64.362383 | I40: =I39-I38 -> 98.1051 | ... M40: =M39-M38 -> 124.54547 | O40: =AVERAGE(B40:N40) -> 46.880058
A41: Margen por Hora (%) | B41: =IFERROR(B40/B39,0) -> 0.12951726 | C41: =IFERROR(C40/C39,0) -> 0.15235567 | D41: =IFERROR(D40/D39,0) -> 0.26273287 | E41: =IFERROR(E40/E39,0) -> 0.082464777 | F41: =IFERROR(F40/F39,0) -> 0.04544861 | G41: =IFERROR(G40/G39,0) -> -0.043855667 | H41: =IFERROR(H40/H39,0) -> 0.10341916 | I41: =IFERROR(I40/I39,0) -> 0.16885353 | ... M41: =IFERROR(M40/M39,0) -> 0.19056492 | O41: =AVERAGE(B41:N41) -> 0.071443759
A43: 5. ANÁLISIS ENERGÉTICO — CHILLER 24/7 vs HORARIO PÚBLICO
A44: Horas Totales Chiller/mes (24hrs × días del mes) | B44: 744 | C44: 672 | D44: 744 | E44: 720 | F44: 744 | G44: 720 | H44: 744 | I44: 744 | J44: 720 | K44: 744 | L44: 720 | M44: 744 | O44: =SUM(B44:N44) -> 8760
A45: Energía Eléctrica Mensual (del P&L) | B45: ='P&L Gerencial'!C11 -> 22754.51 | C45: ='P&L Gerencial'!D11 -> 24839.76 | D45: ='P&L Gerencial'!E11 -> 23204.47 | E45: ='P&L Gerencial'!F11 -> 22781.98 | F45: ='P&L Gerencial'!G11 -> 20410.69 | G45: ='P&L Gerencial'!H11 -> 18773.92 | H45: ='P&L Gerencial'!I11 -> 17726.41 | I45: ='P&L Gerencial'!J11 -> 17115.76 | ... M45: ='P&L Gerencial'!N11 -> 18987.72 | O45: =SUM(B45:N45) -> 238552.34
A46: Costo Energía por Hora de Chiller (S/hr) | B46: =IFERROR(B45/B44,0) -> 30.584019 | C46: =IFERROR(C45/C44,0) -> 36.963929 | D46: =IFERROR(D45/D44,0) -> 31.188804 | E46: =IFERROR(E45/E44,0) -> 31.641639 | F46: =IFERROR(F45/F44,0) -> 27.433723 | G46: =IFERROR(G45/G44,0) -> 26.074889 | H46: =IFERROR(H45/H44,0) -> 23.82582 | I46: =IFERROR(I45/I44,0) -> 23.005054 | ... M46: =IFERROR(M45/M44,0) -> 25.521129 | O46: =AVERAGE(B46:N46) -> 27.303895
A47: Costo Energía por Hora de Público recreativo (S/hr) | B47: =IFERROR(B45/B22,0) -> 75.974992 | C47: =IFERROR(C45/C22,0) -> 91.524539 | D47: =IFERROR(D45/D22,0) -> 77.091262 | E47: =IFERROR(E45/E22,0) -> 79.104097 | F47: =IFERROR(F45/F22,0) -> 67.052201 | G47: =IFERROR(G45/G22,0) -> 64.849465 | H47: =IFERROR(H45/H22,0) -> 59.484597 | I47: =IFERROR(I45/I22,0) -> 55.952141 | ... M47: =IFERROR(M45/M22,0) -> 64.430675 | O47: =AVERAGE(B47:N47) -> 67.693069
A48: % Energía Eléctrica sobre Ingresos — Fórmula: Energía del P&L / Ingresos del P&L | B48: =IFERROR(B45/B18,0) -> 0.1182851 | C48: =IFERROR(C45/C18,0) -> 0.11591257 | D48: =IFERROR(D45/D18,0) -> 0.14589947 | E48: =IFERROR(E45/E18,0) -> 0.14028753 | F48: =IFERROR(F45/F18,0) -> 0.13917415 | G48: =IFERROR(G45/G18,0) -> 0.12623465 | H48: =IFERROR(H45/H18,0) -> 0.095581411 | I48: =IFERROR(I45/I18,0) -> 0.096301993 | ... M48: =IFERROR(M45/M18,0) -> 0.098584286 | O48: =IFERROR(O45/O18,0) -> 0.1191068
A50: 6. RESUMEN KPIs GERENCIALES MENSUALES
A51: KPI | B51: ENE | C51: FEB | D51: MAR | E51: ABR | F51: MAY | G51: JUN | H51: JUL | I51: AGO | J51: SET | K51: OCT | L51: NOV | M51: DIC | N51: PROM/TOTAL
A52: % Ocupación Pista | B52: =B27 -> 0.21145238 | C52: =C27 -> 0.25993306 | D52: =D27 -> 0.17393982 | E52: =E27 -> 0.18563494 | F52: =F27 -> 0.15861796 | G52: =G27 -> 0.16914206 | H52: =H27 -> 0.20490392 | I52: =I27 -> 0.19130246 | ... M52: =M27 -> 0.2151747 | O52: =AVERAGE(B52:N52) -> 0.18704204
A53: Visitas/Hora Disponible | B53: =B29 -> 15.472454 | C53: =C29 -> 19.019897 | D53: =D29 -> 12.727575 | E53: =E29 -> 13.583333 | F53: =F29 -> 11.606439 | G53: =G29 -> 12.376511 | H53: =H29 -> 14.993289 | I53: =I29 -> 13.998039 | ... M53: =M29 -> 15.744825 | O53: =AVERAGE(B53:N53) -> 13.686294
A54: Ingreso por Hora (S/) | B54: =B39 -> 642.30397 | C54: =C39 -> 789.59978 | D54: =D39 -> 528.38618 | E54: =E39 -> 563.87122 | F54: =F39 -> 481.7863 | G54: =G39 -> 513.72159 | H54: =H39 -> 622.34483 | I54: =I39 -> 581.00709 | ... M54: =M39 -> 653.55928 | O54: =AVERAGE(B54:N54) -> 568.12653
A55: Costo Op. Hielo/Hora (S/) | B55: =B36 -> 162.01903 | C55: =C36 -> 168.04598 | D55: =D36 -> 97.014651 | E55: =E36 -> 163.9617 | F55: =F36 -> 139.20733 | G55: =G36 -> 140.66812 | H55: =H36 -> 141.63829 | I55: =I36 -> 132.79843 | ... M55: =M36 -> 138.9944 | O55: =AVERAGE(B55:N55) -> 146.26511
A56: Costo Personal/Hora (S/) | B56: =B37 -> 150.4625 | C56: =C37 -> 248.40822 | D56: =D37 -> 100.96 | E56: =E37 -> 134.37764 | F56: =F37 -> 107.4384 | G56: =G37 -> 120.66218 | H56: =H37 -> 182.03124 | I56: =I37 -> 143.5168 | ... M56: =M37 -> 162.90784 | O56: =AVERAGE(B56:N56) -> 147.11383
A57: Costo Total/Hora (S/) | B57: =B38 -> 559.11452 | C57: =C38 -> 669.29978 | D57: =D38 -> 389.56176 | E57: =E38 -> 517.3717 | F57: =F38 -> 459.88978 | G57: =G38 -> 536.25119 | H57: =H38 -> 557.98245 | I57: =I38 -> 482.90199 | ... M57: =M38 -> 529.01381 | O57: =AVERAGE(B57:N57) -> 521.24647
A58: Margen por Hora (S/) | B58: =B40 -> 83.189449 | C58: =C40 -> 120.3 | D58: =D40 -> 138.82442 | E58: =E40 -> 46.499514 | F58: =F40 -> 21.896518 | G58: =G40 -> -22.529603 | H58: =H40 -> 64.362383 | I58: =I40 -> 98.1051 | ... M58: =M40 -> 124.54547 | O58: =AVERAGE(B58:N58) -> 46.880058
A59: EBITDA Mensual (S/) | B59: ='P&L Gerencial'!C101 -> 24915.24 | C59: ='P&L Gerencial'!D101 -> 32649.42 | D59: ='P&L Gerencial'!E101 -> 41786.15 | E59: ='P&L Gerencial'!F101 -> 13391.86 | F59: ='P&L Gerencial'!G101 -> 6665.3 | G59: ='P&L Gerencial'!H101 -> -6522.32 | H59: ='P&L Gerencial'!I101 -> 19179.99 | I59: ='P&L Gerencial'!J101 -> 30010.35 | ... M59: ='P&L Gerencial'!N101 -> 36703.55 | O59: =SUM(B59:N59) -> 165672.59

Sheet Punto de Equilibrio
A1: PERU ON ICE — ANÁLISIS DE PUNTO DE EQUILIBRIO (BREAK-EVEN)
A2: Todos los cálculos se actualizan automáticamente con los datos del P&L Gerencial e Indicadores Operativos
A4: 1. ESTRUCTURA DE COSTOS ANUAL 2025
A5: Ingresos Reales 2025 | B5: ='P&L Gerencial'!O6 -> 2002844 | C5: Fuente: P&L Gerencial
A6: Costos Operativos del Hielo (B) | B6: ='P&L Gerencial'!O24 -> 515452.91 | C6: Energía + Chiller + Operación directa
A7: Costo de Personal (C) | B7: ='P&L Gerencial'!O46 -> 517339.64 | C7: Planilla completa + cargas sociales
A8: Gastos Comerciales (D) | B8: ='P&L Gerencial'!O57 -> 105699.39 | C8: Marketing + comisiones
A9: Gastos Administrativos (E) | B9: ='P&L Gerencial'!O81 -> 75929.34 | C9: Asesorías + tributos + seguros
A10: Gastos de Estructura (F) | B10: ='P&L Gerencial'!O99 -> 622750.09 | C10: Alquiler local + servicios fijos
A12: 2. CLASIFICACIÓN: COSTOS FIJOS VS. VARIABLES
A13: (+) Costos Fijos Totales | B13: =B6+B7+B9+B10 -> 1731472 | C13: Op. Hielo + Personal + Adm. + Estructura
A14: (−) Costos Variables Totales | B14: =B8 -> 105699.39 | C14: Comercial: comisiones proporcionales a ventas
A15: % Costos Variables sobre Ventas | B15: =IFERROR(B14/B5,0) -> 0.052774651 | C15: Ratio para cálculo de punto de equilibrio
A16: Margen de Contribución (%) | B16: =1-B15 -> 0.94722535 | C16: % que queda de cada s/ de ingreso para cubrir costos fijos
A17: Margen de Contribución (S/) | B17: =IFERROR(B5*B16,0) -> 1897144.6 | C17: total disponible para cubrir costos fijos
A19: 3. PUNTO DE EQUILIBRIO — RESULTADOS
A20: ▶ Punto de equilibrio en VENTAS ANUALES (S/) | B20: =IFERROR(B13/B16,0) -> 1827940.9 | C20: ingresos mínimos anuales para cubrir todos los costos
A21: ▶ Punto de equilibrio MENSUAL Promedio (S/) | B21: =B20/12 -> 152328.41 | C21: ingresos mínimos por mes
A22: Punto de equilibrio como % de Ingresos Reales | B22: =IFERROR(B20/B5,0) -> 0.91267266 | C22: < 100% = negocio con margen positivo
A24: 4. PUNTO DE EQUILIBRIO EN HORAS Y OCUPACIÓN
A25: Ingreso Promedio por Hora Disponible (S/) | B25: =AVERAGE('Indicadores Operativos'!B39:N39) -> 568.12653 | C25: Revenue / Horas disponibles — NO confundir con ticket/persona (S/41.5)
A26: Horas Disponibles Anuales | B26: ='Indicadores Operativos'!O22 -> 3534.3 | C26: Del Driver Operativo
A27: ▶ Punto de equilibrio en HORAS DE USO ANUALES | B27: =IFERROR(B20/B25,0) -> 3217.4891 | C27: horas de pista necesarias público recreativo para punto de equilibrio
A28: ▶ Punto de equilibrio en % OCUPACIÓN | B28: =IFERROR(B27/B26,0) -> 0.91036107 | C28: % ocupación mínimo para cubrir todos los costos
A29: Ocupación Real 2025 (estimada) | B29: =AVERAGE('Indicadores Operativos'!B27:N27) -> 0.18704204 | C29: Promedio anual ocupación real estimada
A30: GAP Ocupación (Real − Punto de equilibrio) | B30: =B29-B28 -> -0.72331903 | C30: Positivo = margen de seguridad sobre el break-even
A32: 5. ANÁLISIS DE SENSIBILIDAD — IMPACTO DE CAMBIOS EN PRECIO Y OCUPACIÓN
A33: Variación del BE ante cambios en precio promedio/hora:
A34: Precio -20% | B34: =IFERROR((B13/(1-B15))/(B25*(1+-0.2))/B26,0) -> 1.1379513 | C34: ocupación mínima para BE
A35: Precio -10% | B35: =IFERROR((B13/(1-B15))/(B25*(1+-0.1))/B26,0) -> 1.0115123 | C35: ocupación mínima para BE
A36: Precio +0% | B36: =IFERROR((B13/(1-B15))/(B25*(1+0))/B26,0) -> 0.91036107 | C36: ocupación mínima para BE
A37: Precio +10% | B37: =IFERROR((B13/(1-B15))/(B25*(1+0.1))/B26,0) -> 0.82760097 | C37: ocupación mínima para BE
A38: Precio +20% | B38: =IFERROR((B13/(1-B15))/(B25*(1+0.2))/B26,0) -> 0.75863422 | C38: ocupación mínima para BE
A40: 6. PUNTO DE EQUILIBRIO POR PERSONA — ANÁLISIS DE TARIFAS (PRECIOS NETOS SIN IGV)
A41: PRODUCTO / TARIFA | B41: PRECIO NETO S/IGV (S/) | C41: COSTO VAR. POR PERSONA | D41: CONTRIBUCIÓN / PERSONA (S/) | E41: PERSONAS BE / AÑO | F41: PERSONAS BE / MES | G41: PERSONAS BE/DÍA (30 días/mes)
A42: Entrada 25 minutos | B42: =Simulador!D6 -> 33.9 | C42: =B42*B15 -> 1.7890607 | D42: =B42-C42 -> 32.110939 | E42: =IFERROR(ROUND(B13/D42,0),0) -> 53922 | F42: =IFERROR(ROUND(E42/12,0),0) -> 4494 | G42: =IFERROR(ROUND(F42/30,0),0) -> 150
A43: Entrada 55 minutos | B43: =Simulador!D7 -> 59.32 | C43: =B43*B15 -> 3.1305923 | D43: =B43-C43 -> 56.189408 | E43: =IFERROR(ROUND(B13/D43,0),0) -> 30815 | F43: =IFERROR(ROUND(E43/12,0),0) -> 2568 | G43: =IFERROR(ROUND(F43/30,0),0) -> 86
A44: Membresía Coach/mes | B44: =Simulador!D8 -> 186.44 | C44: =B44*B15 -> 9.8393058 | D44: =B44-C44 -> 176.60069 | E44: =IFERROR(ROUND(B13/D44,0),0) -> 9804 | F44: =IFERROR(ROUND(E44/12,0),0) -> 817 | G44: =IFERROR(ROUND(F44/30,0),0) -> 27
A45: Membresía Deportistas/mes | B45: =Simulador!D9 -> 296.61 | C45: =B45*B15 -> 15.653489 | D45: =B45-C45 -> 280.95651 | E45: =IFERROR(ROUND(B13/D45,0),0) -> 6163 | F45: =IFERROR(ROUND(E45/12,0),0) -> 514 | G45: =IFERROR(ROUND(F45/30,0),0) -> 17
A46: Salón Off-Ice | B46: =Simulador!D10 -> 50.85 | C46: =B46*B15 -> 2.683591 | D46: =B46-C46 -> 48.166409 | E46: =IFERROR(ROUND(B13/D46,0),0) -> 35948 | F46: =IFERROR(ROUND(E46/12,0),0) -> 2996 | G46: =IFERROR(ROUND(F46/30,0),0) -> 100
A47: ★ Mix Real — Ticket Neto S/IGV (P&L ya excluye IGV) | B47: ='Indicadores Operativos'!B14 -> 41.51 | C47: =B47*B15 -> 2.1906757 | D47: =B47-C47 -> 39.319324 | E47: =IFERROR(ROUND(B13/D47,0),0) -> 44036 | F47: =IFERROR(ROUND(E47/12,0),0) -> 3670 | G47: =IFERROR(ROUND(F47/30,0),0) -> 122
A49: 7. COMPARATIVO: VISITAS REALES 2025 vs PUNTO DE EQUILIBRIO
A50: MÉTRICA | B50: ANUAL | C50: MENSUAL PROM. | D50: DIARIO PROM. (30 días) | E50: DIARIO PROM. (30 días) | F50: ESTADO
A51: Visitas necesarias (BE mix real) | B51: =E47 -> 44036 | C51: =ROUND(B51/12,0) -> 3670 | D51: =ROUND(C51/30,0) -> 122 | E51: =ROUND(C51/30,0) -> 122 | F51: Mínimo para cubrir costos
A52: Visitas reales 2025 | B52: ='Indicadores Operativos'!O15 -> 48249 | C52: =ROUND('Indicadores Operativos'!O15/12,0) -> 4021 | D52: =ROUND(C52/30,0) -> 134 | E52: =ROUND(C52/30,0) -> 134 | F52: Fuente: P&L Gerencial 2025
A53: Excedente / Déficit | B53: =B52-B51 -> 4213 | C53: =C52-C51 -> 351 | D53: =D52-D51 -> 12 | E53: =E52-E51 -> 12 | F53: Positivo = sobre el BE (Punto de equilibrio)
A55: 8. BREAK-EVEN DIARIO POR FRANJA HORARIA — PERSONAS NECESARIAS POR HORA
A56: FRANJA / SUPUESTO | B56: HORAS DISP./DÍA | C56: PERSONAS BE/DÍA | D56: PERSONAS BE/HORA | E56: AFORO PISTA (40 pax) | F56: % USO AFORO NECESARIO
A57: Promedio mensual (30 días/mes) | B57: =ROUND('Indicadores Operativos'!O22/12/30,2) -> 9.82 | C57: =ROUND(E47/12/30,0) -> 122 | D57: =IFERROR(ROUND(C57/B57,1),0) -> 12.4 | E57: 40 | F57: =IFERROR(D57/E57,0) -> 0.31
A58: Día semana L/M (6.67 hrs público) | B58: 6.67 | C58: =ROUND(E47/12/30,0) -> 122 | D58: =IFERROR(ROUND(C58/B58,1),0) -> 18.3 | E58: 40 | F58: =IFERROR(D58/E58,0) -> 0.4575
A59: Día semana M/J (10 hrs público) | B59: 10 | C59: =ROUND(E47/12/30,0) -> 122 | D59: =IFERROR(ROUND(C59/B59,1),0) -> 12.2 | E59: 40 | F59: =IFERROR(D59/E59,0) -> 0.305
A60: Fin de semana (11.5 hrs público) | B60: 11.5 | C60: =ROUND(E47/12/30,0) -> 122 | D60: =IFERROR(ROUND(C60/B60,1),0) -> 10.6 | E60: 40 | F60: =IFERROR(D60/E60,0) -> 0.265
A62: 📌 INTERPRETACIÓN: Todos los precios son NETOS sin IGV (el cliente paga con IGV incluido). La tasa IGV se configura en Simulador celda B13 (actualmente 18%). El Mix Real refleja el ticket neto promedio de febrero 2025 (P&L ya está sin IGV). Si se cambia tarifas en el Simulador, esta sección se actualiza automáticamente.

Sheet Estrategia de Precios
A1: PERU ON ICE S.A.C. — ESTRATEGIA DE PRECIOS Y HOJA DE RUTA HACIA EL 30% DE MARGEN EBITDA
A2: Diagnóstico 2025 | Propuesta tarifaria 2026 | Palancas de mejora | Metas por línea del P&L | Moneda: S/ sin IGV
A4: MARGEN EBITDA 2025 | C4: EBITDA 2025 (S/) | E4: GAP A CERRAR | G4: VISITAS/DÍA 2025 | I4: OCUP. ACTUAL
A5: 0.082718671 | C5: 165672.59 | E5: 672378.79 | G5: 132.18904 | I5: 0.187
A6: Actual — objetivo: 30% | C6: vs target S/600,853 | E6: Revenue adicional necesario | G6: Target: 180+ visitas/día | I6: Target: 35%+ en horario pico
A8: ▌ BLOQUE 1 — NUEVA ESTRUCTURA DE TARIFAS PROPUESTAS
A9: CATEGORÍA | B9: SERVICIO / DESCRIPCIÓN | C9: MIN | D9: PRECIO c/IGV | E9: IGV (18%) | F9: PRECIO NETO s/IGV | G9: PRECIO ANT. s/IGV | H9: VARIACIÓN | I9: MEMBRESÍA c/IGV | J9: MBR NETO s/IGV | K9: TIPO / OBSERVACIÓN
A10: PÚBLICO GENERAL | B10: Entrada estándar | C10: 25 | D10: 40 | E10: 6.1 | F10: 33.9 | G10: 29.66 | H10: 0.14291429 | I10: — | J10: — | K10: Tarifa principal — turno 25 min en pista
A11: PÚBLICO GENERAL | B11: Entrada extendida | C11: 55 | D11: 65 | E11: 9.92 | F11: 55.08 | G11: 50.85 | H11: 0.08324 | I11: — | J11: — | K11: Turno 55 min en pista
A12: PÚBLICO GENERAL | B12: Full Day | C12: — | D12: 150 | E12: 22.88 | F12: 127.12 | G12: — | H12: 🆕 NUEVO | I12: — | J12: — | K12: Acceso todo el día (horario público)
A13: FREE PRACTICE | B13: 5AM – 9AM | C13: 60 | D13: 40 | E13: 6.1 | F13: 33.9 | G13: — | H13: 🆕 NUEVO | I13: — | J13: — | K13: Entrenamiento libre madrugada, 1 hr
A14: CLUBES | B14: Solo horario de clases | C14: — | D14: — | E14: — | F14: — | G14: — | H14: — | I14: 350 | J14: 296.61 | K14: Membresía mensual
A15: OFF ICE – CLUBES | B15: Horario de clases x hora | C15: 60 | D15: 60 | E15: 9.15 | F15: 50.85 | G15: — | H15: 🆕 NUEVO | I15: — | J15: — | K15: Uso salón Off-Ice durante clases
A16: COACHES | B16: Clases particulares x hora | C16: 60 | D16: 30 | E16: 4.58 | F16: 25.42 | G16: 25.42 | H16: — | I16: 250 | J16: 211.86 | K16: Membresía mensual
A17: SOLO ENTRENAMIENTO | B17: Coach 5AM – 9AM | C17: — | D17: 20 | E17: 3.05 | F17: 16.95 | G17: — | H17: 🆕 NUEVO | I17: 200 | J17: 169.49 | K17: Membresía mensual
A18: OFF ICE | B18: Clase x hora | C18: 60 | D18: 80 | E18: 12.2 | F18: 67.8 | G18: — | H18: 🆕 NUEVO | I18: — | J18: — | K18: Salón Off-Ice sin pista
A19: PACKS CLASES | B19: Pack 600 min particulares | C19: 600 | D19: 300 | E19: 45.76 | F19: 254.24 | G19: — | H19: 🆕 NUEVO | I19: — | J19: — | K19: 10 hrs de clases particulares
A20: PACKS CLASES | B20: Pack 1200 min particulares | C20: 1200 | D20: 450 | E20: 68.64 | F20: 381.36 | G20: — | H20: 🆕 NUEVO | I20: — | J20: — | K20: 20 hrs de clases particulares — mayor volumen
A21: CLASES CLUB POI | B21: Pack 240 min | C21: 240 | D21: 380 | E21: 57.97 | F21: 322.03 | G21: — | H21: 🆕 NUEVO | I21: — | J21: — | K21: 4 hrs clases Club POI
A22: CLASES CLUB POI | B22: Pack 480 min | C22: 480 | D22: 760 | E22: 115.93 | F22: 644.07 | G22: — | H22: 🆕 NUEVO | I22: — | J22: — | K22: 8 hrs clases Club POI
A23: SOCIAL | B23: CONADIS | C23: — | D23: GRATIS | E23: — | F23: — | G23: — | H23: — | I23: — | K23: Acceso gratuito — responsabilidad social
A24: SOCIAL | B24: Cumpleañero acompañado | C24: — | D24: GRATIS | E24: — | F24: — | G24: — | H24: — | I24: — | K24: Gratuito si viene con grupo — genera visitas pagadas
A26: ▌ BLOQUE 2 — SIMULACIÓN DE INGRESOS MENSUALES CON NUEVAS TARIFAS
A27: CATEGORÍA | B27: SERVICIO | C27: PRECIO NETO (S/) | D27: VOLUMEN/MES (editable) | E27: INGRESO/MES (S/) | F27: INGRESO/AÑO (S/) | G27: % DEL TOTAL | H27: CV (5.3%) | I27: CONTRIBUCIÓN/MES | K27: NOTA
A28: PÚBLICO GENERAL | B28: Entrada estándar | C28: 33.9 | D28: 3200 | E28: =C28*D28 -> 108480 | F28: =E28*12 -> 1301760 | G28: =IFERROR(E28/E43,0) -> 0.51459734 | H28: =E28*0.0528 -> 5727.744 | I28: =E28-H28 -> 102752.26 | K28: Base: -15% volumen vs 2025, +14% precio → mayor ticket unitario
A29: PÚBLICO GENERAL | B29: Entrada extendida | C29: 55.08 | D29: 1100 | E29: =C29*D29 -> 60588 | F29: =E29*12 -> 727056 | G29: =IFERROR(E29/E43,0) -> 0.28741172 | H29: =E29*0.0528 -> 3199.0464 | I29: =E29-H29 -> 57388.954 | K29: Base conservadora ajustada
A30: PÚBLICO GENERAL | B30: Full Day | C30: 127.12 | D30: 10 | E30: =C30*D30 -> 1271.2 | F30: =E30*12 -> 15254.4 | G30: =IFERROR(E30/E43,0) -> 0.0060302003 | H30: =E30*0.0528 -> 67.11936 | I30: =E30-H30 -> 1204.0806 | K30: Nuevo producto — alta elasticidad en temporada alta
A31: FREE PRACTICE | B31: 5AM – 9AM | C31: 33.9 | D31: 90 | E31: =C31*D31 -> 3051 | F31: =E31*12 -> 36612 | G31: =IFERROR(E31/E43,0) -> 0.01447305 | H31: =E31*0.0528 -> 161.0928 | I31: =E31-H31 -> 2889.9072 | K31: Nuevo segmento: atletas y entusiastas tempranos
A32: CLUBES | B32: Solo horario de clases | C32: 296.61 | D32: 70 | E32: =C32*D32 -> 20762.7 | F32: =E32*12 -> 249152.4 | G32: =IFERROR(E32/E43,0) -> 0.098492165 | H32: =E32*0.0528 -> 1096.2706 | I32: =E32-H32 -> 19666.429 | K32: Membresía actual mantenida — base de ingresos recurrentes
A33: OFF ICE – CLUBES | B33: Horario de clases x hora | C33: 50.85 | D33: 60 | E33: =C33*D33 -> 3051 | F33: =E33*12 -> 36612 | G33: =IFERROR(E33/E43,0) -> 0.01447305 | H33: =E33*0.0528 -> 161.0928 | I33: =E33-H33 -> 2889.9072 | K33: Nuevo: monetiza el espacio fuera del hielo
A34: COACHES | B34: Clases particulares x hora | C34: 25.42 | D34: 10 | E34: =C34*D34 -> 254.2 | F34: =E34*12 -> 3050.4 | G34: =IFERROR(E34/E43,0) -> 0.0012058503 | H34: =E34*0.0528 -> 13.42176 | I34: =E34-H34 -> 240.77824 | K34: Nuevo: clases privadas son el mayor margen por hora
A35: SOLO ENTRENAMIENTO | B35: Coach 5AM – 9AM | C35: 16.95 | D35: 10 | E35: =C35*D35 -> 169.5 | F35: =E35*12 -> 2034 | G35: =IFERROR(E35/E43,0) -> 0.00080405834 | H35: =E35*0.0528 -> 8.9496 | I35: =E35-H35 -> 160.5504 | K35: Nuevo: acceso premium madrugada
A36: OFF ICE | B36: Clase x hora | C36: 67.8 | D36: 10 | E36: =C36*D36 -> 678 | F36: =E36*12 -> 8136 | G36: =IFERROR(E36/E43,0) -> 0.0032162333 | H36: =E36*0.0528 -> 35.7984 | I36: =E36-H36 -> 642.2016 | K36: Nuevo: Off-Ice sin pista = costo marginal casi cero
A37: PACKS CLASES | B37: Pack 600 min particulares | C37: 254.24 | D37: 10 | E37: =C37*D37 -> 2542.4 | F37: =E37*12 -> 30508.8 | G37: =IFERROR(E37/E43,0) -> 0.012060401 | H37: =E37*0.0528 -> 134.23872 | I37: =E37-H37 -> 2408.1613 | K37: Nuevo: pack de horas — genera ingreso anticipado
A38: PACKS CLASES | B38: Pack 1200 min particulares | C38: 381.36 | D38: 5 | E38: =C38*D38 -> 1906.8 | F38: =E38*12 -> 22881.6 | G38: =IFERROR(E38/E43,0) -> 0.0090453005 | H38: =E38*0.0528 -> 100.67904 | I38: =E38-H38 -> 1806.121 | K38: Nuevo: máximo descuento por volumen alto
A39: CLASES CLUB POI | B39: Pack 240 min | C39: 322.03 | D39: 15 | E39: =C39*D39 -> 4830.45 | F39: =E39*12 -> 57965.4 | G39: =IFERROR(E39/E43,0) -> 0.022914239 | H39: =E39*0.0528 -> 255.04776 | I39: =E39-H39 -> 4575.4022 | K39: Nuevo: Club POI — base de fans
A40: CLASES CLUB POI | B40: Pack 480 min | C40: 644.07 | D40: 5 | E40: =C40*D40 -> 3220.35 | F40: =E40*12 -> 38644.2 | G40: =IFERROR(E40/E43,0) -> 0.015276397 | H40: =E40*0.0528 -> 170.03448 | I40: =E40-H40 -> 3050.3155 | K40: Nuevo: pack POI — compromiso largo plazo
A41: SOCIAL | B41: CONADIS | C41: — | D41: 0 | E41: GRATIS | F41: — | G41: — | H41: — | I41: — | K41: Responsabilidad social — sin impacto en margen
A42: SOCIAL | B42: Cumpleañero acompañado | C42: — | D42: 0 | E42: GRATIS | F42: — | G42: — | H42: — | I42: — | K42: Generador de visitas pagadas del grupo acompañante
A43: TOTAL INGRESOS / MES | E43: =E28+E29+E30+E31+E32+E33+E34+E35+E36+E37+E38+E39+E40 -> 210805.6 | F43: =F28+F29+F30+F31+F32+F33+F34+F35+F36+F37+F38+F39+F40 -> 2529667.2 | H43: =E43*0.0528 -> 11130.536 | I43: =E43-H43 -> 199675.06
A45: ▌ BLOQUE 3 — MODELO DE RENTABILIDAD: CAMINO AL 30% DE MARGEN EBITDA
A46: CONCEPTO | B46: ACTUAL 2025 | C46: NUEVO TARIF. (sin ajuste CF) | D46: NUEVO TARIF. + AJUSTE CF | E46: META 30% (referencia) | F46: OBSERVACIÓN
A47: Ingresos Mensuales (S/) | B47: 166903.66 | C47: 214009.11 | D47: 214009.11 | E47: 222935.23 | F47: Ingresos por mes
A48: Ingresos Anuales (S/) | B48: 2002844 | C48: 2568109.3 | D48: 2568109.3 | E48: 2675222.8 | F48: 2025 real vs proyección nuevas tarifas
A49: Costos Fijos Totales (S/) | B49: 1731472 | C49: 1731472 | D49: 1611472 | E49: 1731472 | F49: Actual: S/1,731,472 | Propuesta: reducir S/120K (ver Bloque 4)
A50: Costos Variables (5.3%) | B50: 105699.39 | C50: 135531.07 | D50: 135531.07 | E50: 141183.95 | F50: Comisiones tarjeta y ventas proporcionales
A51: EBITDA Anual (S/) | B51: 165672.59 | C51: 701106.27 | D51: 821106.27 | E51: 802566.83 | F51: Resultado operativo antes de depreciación y financiero
A52: Margen EBITDA (%) | B52: 0.082718671 | C52: 0.27300484 | D52: 0.31973182 | E52: 0.3 | F52: 2025: 8.3% | Con solo tarifas: ¿suficiente? | Con CF ajustado: ¿llega?
A53: Visitas mensuales necesarias | B53: 4020.75 | C53: 186.23212 | D53: 186.23212 | E53: 193.99968 | F53: Estimado en base a ticket promedio propuesto
A55: ▌ BLOQUE 4 — RECOMENDACIONES ACCIONABLES: AJUSTES EN LÍNEAS DEL P&L
A56: LÍNEA P&L / CUENTA | B56: VALOR 2025 (S/) | C56: % INGRESOS | D56: ACCIÓN PROPUESTA | E56: AHORRO / IMPACTO EST. | F56: PRIORIDAD | G56: RESPONSABLE / PLAZO | H56: DETALLE
A57: F. ALQUILER LOCAL | B57: 583542.5 | C57: 0.291 | D57: Renegociar contrato — proponer renta variable ligada al % de ventas (20% de ventas con piso S/40,000/mes) | E57: ▲ Ahorro potencial: S/100,000–150,000/año si se vincula a % revenue | F57: 🔴 CRÍTICA | G57: Gerente General | Q2 2026 | H57: Es el costo más alto: 29.1% de ingresos. Cláusula actual: fija. Meta: piso S/40K + 20% sobre exceso → en meses bajos reduce exposición
A58: B. ENERGÍA ELÉCTRICA | B58: 238552.34 | C58: 0.119 | D58: Auditoría energética: Implementacion Fire it up, iluminación LED, tarifa BT3 fuera de punta | E58: ▲ Ahorro 15-20%: S/35,000–48,000/año en consumo operativo | F58: 🔴 CRÍTICA | G58: Gerente de sede -Operaciones | Q1 2026 | H58: El chiller es 24/7 (costo fijo de refrigeración), pero iluminación, bombas secundarias y HVAC son controlables. ROI de inversión: 12-18 meses
A59: B. CHILLER | B59: 209000 | C59: 0.104 | D59: Evaluar compra del equipo vs. arrendamiento. A S/209K/año, en 5-7 años se paga solo con deuda bancaria a 8% | E59: ▲ Ahorro neto potencial: S/80,000–120,000/año vs. costo actual de arrendamiento | F59: 🟠 ALTA | G59: Gerente Gral | Q3 2026 | H59: Financiamiento de equipo nuevo (aprox. USD 80K-120K) vs. S/209K/año en arriendo. Payback ~5 años. Reduce CF fijo significativamente
A60: C. SUELDOS Y SALARIOS | B60: 280134.96 | C60: 0.14 | D60: Implementar scheduling por demanda: reducir HH en días de semana con baja afluencia (MAR-JUE tarde), reforzar fines de semana y feriados. (Analizar demanda con nuevo sistema de facturación) | E60: ▲ Optimización 10%: S/28,000/año sin reducir planilla — reasignando turnos | F60: 🟠 ALTA | G60: Gerente de Sede | Q1 2026 | H60: Análisis de ocupación muestra que L/M tienen solo 6.7 hrs públicas vs 11.5 hrs en fin de semana. Turnos deben alinearse a demanda real
A61: C. TOTAL PERSONAL | B61: 517339.64 | C61: 0.258 | D61: Revisar estructura de contratos: evaluar modalidad prestación de servicios para roles no esenciales (marketing, Ssoma, Legal, Tópico) | E61: ▲ Reducción potencial 8-12%: S/41,000–62,000/año | F61: 🟡 MEDIA | G61: Gerente Sede + Asesoria laboral | Q2 2026 | H61: Carga laboral total (gratificaciones, CTS, EsSalud) = 85% adicional sobre sueldo base. Roles de servicios esporádicos pueden ser recategorizados
A62: D. COMISIÓN TARJETA | B62: 42784.83 | C62: 0.021 | D62: Negociar POS con tasa < 1.5%. Incentivar Yape/Plin/transferencia con descuento del 3% (menor que la comisión actual) | E62: ▲ Ahorro S/12,000–15,000/año si se reduce de 2.1% a 1.5% efectivo | F62: 🟡 MEDIA | G62: CFO + Administración | Q1 2026 | H62: Comisión actual ~2.1% sobre ventas. Mercado ofrece 1.2-1.5% para volumes >S/100K/mes. Evaluar otros proveedores
A63: D. EVENTOS Y COMISIONES VENTAS | B63: 39953.44 | C63: 0.02 | D63: Estructurar programa de comisiones solo sobre ventas incrementales. Definir KPIs claros | E63: ▲ Control del gasto + alineación incentivos al crecimiento real | F63: 🟡 MEDIA | G63: Gerente Comercial | Q1 2026 | H63: Comisión de ventas debe ser variable puro. Eventos: cobrar tarifa mínima de producción a clientes corporativos para cubrir costo de servicio
A64: E. AUDITORÍA Y CONTABLE | B64: 24000 | C64: 0.012 | D64: Evaluar si el nivel de servicio justifica S/24,000/año (S/2,000/mes). Licitar con 2-3 estudios contables comparando | E64: ▲ Posible ahorro S/6,000–9,600/año si se optimiza contrato | F64: 🟢 BAJA | G64: Gerente Gral - Junta de Accionistas | Q2 2026 | H64: S/2,000/mes es precio de mercado para empresas medianas. Verificar scope del servicio actual vs. lo que realmente se usa
A65: F. SERVICIOS INFORMÁTICOS/SISTEMAS | B65: 7550 | C65: 0.004 | D65: Consolidó S/6,500 en sistemas + S/1,050 en informáticos en un solo contrato SaaS de gestión para este 2026 | E65: ▲ Ahorro S/4,500/año + mejora en control de ventas y reservas online | F65: 🟢 BAJA | G65: Gerente de Sede | Q1 2026 | H65: Implementar sistema de gestión que centralice reservas, membresías y POS. Reduce trabajo manual y mejora datos
A66: INGRESOS — NUEVOS PRODUCTOS | B66: Ver detalle | C66: — | D66: Activar TODOS los nuevos productos (Off-Ice, Free Practice, Packs, Club POI) con campaña de lanzamiento en Q2 2026 | E66: ▲ Ingreso adicional estimado: S/80,000–120,000/año en los primeros 12 meses | F66: 🔴 CRÍTICA | G66: Área Comercial + Marketing | Inmediato | H66: Full Day, Free Practice madrugada, Packs Clases y Club POI son productos con costo marginal casi cero (pista operando). Cada S/1 adicional va 94.7% a EBITDA
A67: OCUPACIÓN — HORARIO VALLE | B67: Ver detalle | C67: — | D67: MAR-JUE 10AM-4PM: continuar con los programas especiales (escuelas, empresas, grupos). Solo 12-15 personas/hora adicionales cierra el gap al 30% | E67: ▲ 2 grupos/semana de 15 personas × S/40 = S/52,000/año adicional | F67: 🔴 CRÍTICA | G67: Gerente Comercial | Q1 2026 | H67: Los meses JUN, SET, OCT, NOV son negativos. La pista está operativa 24/7, el personal ya está pagado. Cada ingreso adicional es casi 100% margen incremental
A69: ▌ BLOQUE 5 — RESUMEN EJECUTIVO: IMPACTO COMBINADO DE LAS MEDIDAS
A70: PALANCA | B70: IMPACTO EBITDA EST. (S/) | C70: TIPO | D70: PLAZO | E70: COMENTARIO
A71: 1. Nuevos precios (E.25 S/40, E.55 S/65) | B71: + S/48,000–72,000/año | C71: Ingresos | D71: Q1 2026 | E71: Solo con el volumen actual 2025 — sin incrementar visitas
A72: 2. Nuevos productos (Full Day, Free Practice, Packs, Off-Ice) | B72: + S/80,000–120,000/año | C72: Ingresos | D72: Q1-Q2 2026 | E72: Costo marginal - cero: pista congelada, personal ya pagado
A73: 3. Renegociación Alquiler Local | B73: + S/100,000–150,000/año | C73: Costos Fijos | D73: Q2 2026 | E73: Requiere negociación: proponer renta variable con piso
A74: 4. Eficiencia energética | B74: + S/35,000–48,000/año | C74: Costos Fijos | D74: Q1-Q2 2026 | E74: Establecer horarios de apagado de luces y bajar la temperatura del equipo en horas de desuso
A75: 5. Evaluación compra Chiller | B75: + S/80,000–120,000/año | C75: Costos Fijos | D75: Q3 2026 | E75: Inversión de mediano plazo — requiere financiamiento
A76: 6. Optimización planilla | B76: + S/28,000–41,000/año | C76: Costos Fijos | D76: Q1 2026 | E76: Reducir personal — reasignación de ROL a demanda
A77: 7. Activar horario valle (MAR-JUE) | B77: + S/52,000–78,000/año | C77: Ingresos | D77: Q1 2026 | E77: Grupos, escuelas, corporativos — margen incremental ~95%
A78: ★ IMPACTO TOTAL ESTIMADO (escenario conservador) | B78: + S/423,000–579,000/año | C78: EBITDA 2025: S/165,673 (8.3%) | D78: EBITDA META: S/589,000+ (29%+) | E78: Con implementación de las 7 palancas (A71) simultáneas en 2026

Sheet Simulador
A1: PERU ON ICE — SIMULADOR DE INGRESOS POR TARIFAS Y MIX DE PRODUCTOS
A4: 📋 BLOQUE 1: TARIFAS VIGENTES — PRECIOS POR PRODUCTO
A5: PRODUCTO / SERVICIO | B5: PRECIO CON IGV (S/) | C5: IGV (S/) | D5: PRECIO NETO SIN IGV (S/) | E5: DESCRIPCIÓN
A6: Entrada 25 minutos | B6: 40 | C6: =ROUND(B6*$B$13/(1+$B$13),2) -> 6.1 | D6: =ROUND(B6/(1+$B$13),2) -> 33.9
A7: Entrada 55 minutos | B7: 70 | C7: =ROUND(B7*$B$13/(1+$B$13),2) -> 10.68 | D7: =ROUND(B7/(1+$B$13),2) -> 59.32
A8: Membresía Coach | B8: 220 | C8: =ROUND(B8*$B$13/(1+$B$13),2) -> 33.56 | D8: =ROUND(B8/(1+$B$13),2) -> 186.44
A9: Membresía Deportistas | B9: 350 | C9: =ROUND(B9*$B$13/(1+$B$13),2) -> 53.39 | D9: =ROUND(B9/(1+$B$13),2) -> 296.61
A10: Salón Off-Ice | B10: 60 | C10: =ROUND(B10*$B$13/(1+$B$13),2) -> 9.15 | D10: =ROUND(B10/(1+$B$13),2) -> 50.85
A11: 🆕 Nuevo Producto 1 | B11: 0 | C11: =ROUND(B11*$B$13/(1+$B$13),2) -> 0 | D11: =ROUND(B11/(1+$B$13),2) -> 0
A12: 🆕 Nuevo Producto 2 | B12: 0 | C12: =ROUND(B12*$B$13/(1+$B$13),2) -> 0 | D12: =ROUND(B12/(1+$B$13),2) -> 0
A13: ⚙ TASA IGV | B13: 0.18 | C13: ← IGV 18% incluido en el precio al cliente
A14: 📊 BLOQUE 2: VOLUMEN MENSUAL (MES PROMEDIO)
A15: PRODUCTO | B15: CANTIDAD/MES (editable) | C15: PRECIO NETO SIN IGV (S/) | D15: INGRESOS /MES (S/) | E15: INGRESOS/AÑO | F15: % DEL TOTAL | G15: NOTA
A16: Entrada 25 minutos | B16: 3820 | C16: =D6 -> 33.9 | D16: =B16*C16 -> 129498 | E16: =D16*12 -> 1553976 | F16: =IFERROR(D16/D23,0) -> 0.58638093 | G16: Calibrado de Feb 2025: 74% × 5,162 visitas → S/133,700
A17: Entrada 55 minutos | B17: 1342 | C17: =D7 -> 59.32 | D17: =B17*C17 -> 79607.44 | E17: =D17*12 -> 955289.28 | F17: =IFERROR(D17/D23,0) -> 0.36047108 | G17: Calibrado de Feb 2025: 26% × 5,162 visitas → S/80,520
A18: Membresía Coach | B18: 15 | C18: =D8 -> 186.44 | D18: =B18*C18 -> 2796.6 | E18: =D18*12 -> 33559.2 | F18: =IFERROR(D18/D23,0) -> 0.012663307 | G18: Estimado — actualizar con datos reales
A19: Membresía Deportistas | B19: 25 | C19: =D9 -> 296.61 | D19: =B19*C19 -> 7415.25 | E19: =D19*12 -> 88983 | F19: =IFERROR(D19/D23,0) -> 0.033577053 | G19: Estimado — actualizar con datos reales
A20: Salón Off-Ice | B20: 30 | C20: =D10 -> 50.85 | D20: =B20*C20 -> 1525.5 | E20: =D20*12 -> 18306 | F20: =IFERROR(D20/D23,0) -> 0.0069076287 | G20: Estimado — actualizar con datos reales
A21: 🆕 Nuevo Producto 1 | B21: 0 | C21: =D11 -> 0 | D21: =B21*C21 -> 0 | E21: =D21*12 -> 0 | F21: =IFERROR(D21/D23,0) -> 0 | G21: Nuevo producto — ingresa cantidad
A22: 🆕 Nuevo Producto 2 | B22: 0 | C22: =D12 -> 0 | D22: =B22*C22 -> 0 | E22: =D22*12 -> 0 | F22: =IFERROR(D22/D23,0) -> 0 | G22: Nuevo producto — ingresa cantidad
A23: TOTAL INGRESOS / MES | D23: =D16+D17+D18+D19+D20+D21+D22 -> 220842.79 | E23: =D23*12 -> 2650113.5 | F23: 100%
A24: Ticket Promedio Ponderado (S/) | D24: =IFERROR(D23/SUM(B16:B20),0) -> 42.210013
A26: 💰 BLOQUE 3: COSTOS Y EBITDA SIMULADO
A27: CONCEPTO | B27: MENSUAL (S/) | C27: ANUAL (S/) | D27: % INGRESOS | F27: EDITABLE | G27: FUENTE
A28: ( - ) Costos Variables (% ingresos) | B28: 0.0528 | C28: % ingresos | D28: Comis. tarjeta+ventas+marketing. Del P&L 2025.
A29: → Costos Variables S/ | B29: =ROUND(D23*B28,0) -> 11660 | C29: =B29*12 -> 139920 | D29: =IFERROR(B29/D23,0) -> 0.052797739
A30: Margen de Contribución | B30: =D23-B29 -> 209182.79 | C30: =B30*12 -> 2510193.5 | D30: =IFERROR(B30/D23,0) -> 0.94720226
A32: ( - ) Costos Op. Hielo / mes | B32: 42954 | C32: S/ | D32: Del P&L 2025 anual / 12 meses
A33: ( - ) Personal / mes | B33: 43112 | C33: S/ | D33: Del P&L 2025 anual / 12 meses
A34: ( - ) Administrativo / mes | B34: 6327 | C34: S/ | D34: Del P&L 2025 anual / 12 meses
A35: ( - ) Estructura (Alquiler+Servicios) / mes | B35: 51896 | C35: S/ | D35: Del P&L 2025 anual / 12 meses
A36: Total Costos Fijos / mes | B36: =B32+B33+B34+B35 -> 144289 | C36: =B36*12 -> 1731468 | D36: =IFERROR(B36/D23,0) -> 0.65335617
A38: ★★ EBITDA MENSUAL SIMULADO | B38: =B30-B36 -> 64893.79 | C38: =B38*12 -> 778725.48 | D38: =IFERROR(B38/D23,0) -> 0.29384609
A40: 📈 BLOQUE 4: COMPARATIVO vs REAL 2025
A41: MÉTRICA | B41: SIMULADO | C41: BASE 2025 (mensual prom.) | D41: DIFERENCIA (S/) | E41: MEJORA (%)
A42: Ingresos Mensuales (S/) | B42: =D23 -> 220842.79 | C42: 166904 | D42: =B42-C42 -> 53938.79 | E42: =IFERROR((B42-C42)/ABS(C42),0) -> 0.32317254
A43: EBITDA Mensual (S/) | B43: =B38 -> 64893.79 | C43: 13806 | D43: =B43-C43 -> 51087.79 | E43: =IFERROR((B43-C43)/ABS(C43),0) -> 3.7004049
A44: EBITDA Anual (S/) | B44: =C38 -> 778725.48 | C44: 165673 | D44: =B44-C44 -> 613052.48 | E44: =IFERROR((B44-C44)/ABS(C44),0) -> 3.7003765
A45: Margen EBITDA (%) | B45: =D38 -> 0.29384609 | C45: 0.0827 | D45: =B45-C45 -> 0.21114609 | E45: =IFERROR((B45-C45)/ABS(C45),0) -> 2.5531571
A46: Punto de quilibrio Mensual (S/) | B46: =IFERROR(B36/(1-B28),0) -> 152332.14 | C46: 152328 | D46: =B46-C46 -> 4.1368243 | E46: =IFERROR((B46-C46)/ABS(C46),0) -> 2.7157347e-05
A48: 🔍 BLOQUE 5: IMPACTO MARGINAL DE CADA PRODUCTO
A49: SI AGREGO… | B49: CANT./MES | C49: PRECIO | D49: ING. ADICIONAL/MES | E49: EBITDA ADICIONAL/MES | F49: % MARGEN | G49: ANÁLISIS
A50: 10 entradas 25min/día (+300/mes) | B50: 300 | C50: =B6 -> 40 | D50: =B50*C50 -> 12000 | E50: =D50*(1-B28) -> 11366.4 | F50: =IFERROR(E50/D50,0) -> 0.9472 | G50: EBITDA marginal = 100% menos CV
A51: 10 entradas 55min/día (+300/mes) | B51: 300 | C51: =B7 -> 70 | D51: =B51*C51 -> 21000 | E51: =D51*(1-B28) -> 19891.2 | F51: =IFERROR(E51/D51,0) -> 0.9472 | G51: EBITDA marginal = 100% menos CV
A52: 5 nuevas membresías Coach | B52: 5 | C52: =B8 -> 220 | D52: =B52*C52 -> 1100 | E52: =D52*(1-B28) -> 1041.92 | F52: =IFERROR(E52/D52,0) -> 0.9472 | G52: EBITDA marginal = 100% menos CV
A53: 10 nuevas membresías Deportistas | B53: 10 | C53: =B9 -> 350 | D53: =B53*C53 -> 3500 | E53: =D53*(1-B28) -> 3315.2 | F53: =IFERROR(E53/D53,0) -> 0.9472 | G53: EBITDA marginal = 100% menos CV
A54: 20 usos Salón Off-Ice/mes | B54: 20 | C54: =B10 -> 60 | D54: =B54*C54 -> 1200 | E54: =D54*(1-B28) -> 1136.64 | F54: =IFERROR(E54/D54,0) -> 0.9472 | G54: EBITDA marginal = 100% menos CV

Sheet Datos 2026
A1: PERU ON ICE — BASE DE DATOS P&L 2026 (PRESUPUESTO ENE-DIC)
A2: Fuente: P&L 2026 original + proyección +7% sobre 2025
A3: CUENTA | B3: DESCRIPCIÓN | C3: ENE | D3: FEB | E3: MAR | F3: ABR | G3: MAY | H3: JUN | I3: JUL | J3: AGO | K3: SET | L3: OCT | M3: NOV | N3: DIC | O3: TOTAL | P3: % REV.
A4: 7032100 | B4: Servicios-Local-Terceros | C4: 192370.04 | D4: 214297.38 | E4: 170177.34 | F4: 173762.55 | G4: 156921.65 | H4: 159132.97 | I4: 198440.87 | J4: 190171.17 | K4: 149187.06 | L4: 154118.53 | M4: 149910.55 | N4: 206086.19 | O4: =SUM(C4:N4) -> 2114576.3 | P4: =IFERROR(O4/O4,0) -> 1
A5: 7761100 | B5: Diferencia en cambio | C5: 0.69 | D5: 0.94 | E5: 0 | F5: 5.08 | G5: 2.4 | H5: 174.7 | I5: 157.27 | J5: 82.85 | K5: 120.88 | L5: 196.28 | M5: 24.43 | N5: 598.71 | O5: =SUM(C5:N5) -> 1364.23 | P5: =IFERROR(O5/O4,0) -> 0.00064515525
A6: 7761101 | B6: Diferencia de Redondeo | C6: 10.66 | D6: 0.01 | E6: 0.15 | F6: 9.07 | G6: 1.18 | H6: 0.77 | I6: 0 | J6: 10.01 | K6: 0.01 | L6: 0 | M6: 0.03 | N6: 0.06 | O6: =SUM(C6:N6) -> 31.95 | P6: =IFERROR(O6/O4,0) -> 1.510941e-05
A7: 6211100 | B7: Sueldos y salarios | C7: 28638 | D7: 24200 | E7: 26007.68 | F7: 25053 | G7: 24486 | H7: 25517.98 | I7: 25702.6 | J7: 23177 | K7: 23862.54 | L7: 23877 | M7: 21864.5 | N7: 19113.51 | O7: =SUM(C7:N7) -> 291499.81 | P7: =IFERROR(O7/O4,0) -> 0.13785259
A8: 6211101 | B8: Asignacion Familiar | C8: 339 | D8: 226 | E8: 339 | F8: 452 | G8: 452 | H8: 452 | I8: 452 | J8: 452 | K8: 565 | L8: 452 | M8: 565 | N8: 565 | O8: =SUM(C8:N8) -> 5311 | P8: =IFERROR(O8/O4,0) -> 0.0025116143 | T8: 533.33
A9: 6211103 | B9: Rem. Vacacional | C9: 0 | D9: 0 | E9: 0 | F9: 0 | G9: 0 | H9: 0 | I9: 0 | J9: 1000 | K9: 166.67 | L9: 0 | M9: 0 | O9: =SUM(C9:N9) -> 1166.67 | P9: =IFERROR(O9/O4,0) -> 0.00055172755
A10: 6211104 | B10: Rem. por Feriado | C10: 0 | D10: 0 | E10: 0 | F10: 3076.27 | G10: 1538.13 | H10: 3144.93 | I10: 4545.73 | J10: 2437.67 | K10: 0 | L10: 1222.27 | M10: 1496.93 | N10: 4185.23 | O10: =SUM(C10:N10) -> 21647.16 | P10: =IFERROR(O10/O4,0) -> 0.010237115
A11: 6211105 | B11: Movilidad | C11: 100 | D11: 100 | E11: 100 | F11: 100 | G11: 100 | H11: 100 | I11: 100 | J11: 100 | K11: 100 | L11: 100 | M11: 100 | N11: 100 | O11: =SUM(C11:N11) -> 1200 | P11: =IFERROR(O11/O4,0) -> 0.00056748957
A12: 6211106 | B12: Rem. Vacacional Truncas | C12: 0 | D12: 0 | E12: 0 | F12: 379.17 | G12: 563.33 | H12: 150 | I12: 488.38 | J12: 2470 | K12: 2507.46 | L12: 646.67 | M12: 4055 | N12: 26.67 | O12: =SUM(C12:N12) -> 11286.68 | P12: =IFERROR(O12/O4,0) -> 0.005337561
A13: 6212101 | B13: Horas Extras | C13: 2052.13 | D13: 559.31 | E13: 576.09 | F13: 576.09 | G13: 701.98 | H13: 576.09 | I13: 576.09 | J13: 576.09 | K13: 576.09 | L13: 527.16 | M13: 576.09 | N13: 638.66 | O13: =SUM(C13:N13) -> 8511.87 | P13: =IFERROR(O13/O4,0) -> 0.0040253312
A14: 6214100 | B14: Gratificaciones | C14: 818.84 | D14: 8728.04 | E14: 0 | F14: 497.83 | G14: 1030 | H14: 206 | I14: 15888.9 | J14: 1751 | K14: 2213.73 | L14: 1922.67 | M14: 5665 | N14: 15002.17 | O14: =SUM(C14:N14) -> 53724.18 | P14: =IFERROR(O14/O4,0) -> 0.025406593
A15: 6214101 | B15: Bonificacion | C15: 73.7 | D15: 785.52 | E15: 0 | F15: 44.8 | G15: 92.7 | H15: 18.54 | I15: 1430.01 | J15: 157.59 | K15: 199.23 | L15: 173.04 | M15: 509.85 | N15: 1350.2 | O15: =SUM(C15:N15) -> 4835.18 | P15: =IFERROR(O15/O4,0) -> 0.0022865952
A16: 6214103 | B16: Bonificacion Regular | C16: 1859.88 | D16: 1615.48 | E16: 1693 | F16: 2400 | G16: 1400 | H16: 0 | I16: 680 | J16: 3090 | K16: 1580 | L16: 760 | M16: 700 | N16: 280 | O16: =SUM(C16:N16) -> 16058.36 | P16: =IFERROR(O16/O4,0) -> 0.0075941265
A17: 6215100 | B17: Vacaciones | C17: 4354.54 | D17: 20244.97 | E17: 0 | F17: 0 | G17: 0 | H17: 0 | I17: 0 | J17: 0 | K17: 0 | L17: 0 | M17: 0 | N17: 0 | O17: =SUM(C17:N17) -> 24599.51 | P17: =IFERROR(O17/O4,0) -> 0.011633305
A18: 6221100 | B18: Otras remuneraciones | C18: 0 | D18: 1000 | E18: 0 | F18: 0 | G18: 0 | H18: 2080.6 | I18: 1627.4 | J18: 2327.8 | K18: 1630.83 | L18: 2818.77 | M18: 2070.3 | N18: 1448.87 | O18: =SUM(C18:N18) -> 15004.57 | P18: =IFERROR(O18/O4,0) -> 0.0070957808
A19: 6241100 | B19: Capacitacion | C19: 0 | D19: 0 | E19: 0 | F19: 0 | G19: 0 | H19: 0 | I19: 0 | J19: 550 | K19: 0 | L19: 0 | M19: 0 | N19: 0 | O19: =SUM(C19:N19) -> 550 | P19: =IFERROR(O19/O4,0) -> 0.00026009939
A20: 6251100 | B20: Atencion al personal | C20: 1920 | D20: 115.81 | E20: 409.27 | F20: 248.98 | G20: 895.24 | H20: 1142.39 | I20: 1526.16 | J20: 2428.71 | K20: 582.4 | L20: 332.97 | M20: 386.44 | N20: 2645.15 | O20: =SUM(C20:N20) -> 12633.52 | P20: =IFERROR(O20/O4,0) -> 0.0059744924
A21: 6271100 | B21: EsSalud | C21: 3351.92 | D21: 4335.83 | E21: 2665.58 | F21: 2903.23 | G21: 2717.53 | H21: 3011.64 | I21: 2936.27 | J21: 3120.23 | K21: 2789.52 | L21: 2560.68 | M21: 2370.5 | N21: 2503.79 | O21: =SUM(C21:N21) -> 35266.72 | P21: =IFERROR(O21/O4,0) -> 0.016677913
A22: 6273100 | B22: SCTR | C22: 100 | D22: 0 | E22: 0 | F22: 4055.51 | G22: 0 | H22: 0 | I22: 0 | J22: 0 | K22: 0 | L22: 0 | M22: 0 | N22: 0 | O22: =SUM(C22:N22) -> 4155.51 | P22: =IFERROR(O22/O4,0) -> 0.0019651738
A23: 6291100 | B23: CTS | C23: 1455.51 | D23: 5507.03 | E23: 0 | F23: 390.55 | G23: 168.23 | H23: 123.6 | I23: 442.08 | J23: 1949.55 | K23: 2042.25 | L23: 10258.61 | M23: 1937.24 | N23: 1473.63 | O23: =SUM(C23:N23) -> 25748.28 | P23: =IFERROR(O23/O4,0) -> 0.012176567
A24: 6311100 | B24: Transporte de carga | C24: 0 | D24: 0 | E24: 0 | F24: 0 | G24: 0 | H24: 0 | I24: 15.75 | J24: 21 | K24: 0 | L24: 0 | M24: 493.5 | N24: 0 | O24: =SUM(C24:N24) -> 530.25 | P24: =IFERROR(O24/O4,0) -> 0.00025075945
A25: 6311200 | B25: Transporte pasajeros | C25: 0 | D25: 0 | E25: 0 | F25: 0 | G25: 0 | H25: 444.92 | I25: 0 | J25: 0 | K25: 0 | L25: 152.25 | M25: 194.25 | N25: 173.25 | O25: =SUM(C25:N25) -> 964.67 | P25: =IFERROR(O25/O4,0) -> 0.00045620014
A26: 6311201 | B26: Planilla Movilidad | C26: 238.2 | D26: 371.94 | E26: 556.92 | F26: 265.12 | G26: 344.93 | H26: 239.4 | I26: 682.5 | J26: 550.29 | K26: 148.47 | L26: 113.61 | M26: 505.37 | N26: 0 | O26: =SUM(C26:N26) -> 4016.75 | P26: =IFERROR(O26/O4,0) -> 0.0018995531
A27: 6313100 | B27: Alojamiento | C27: 0 | D27: 0 | E27: 0 | F27: 0 | G27: 0 | H27: 127.27 | I27: 0 | J27: 0 | K27: 0 | L27: 0 | M27: 0 | N27: 0 | O27: =SUM(C27:N27) -> 127.27 | P27: =IFERROR(O27/O4,0) -> 6.0186998e-05
A28: 6314100 | B28: Alimentacion | C28: 208 | D28: 128 | E28: 111.83 | F28: 0 | G28: 372.96 | H28: 128.84 | I28: 446.61 | J28: 122.04 | K28: 717.42 | L28: 0 | M28: 0 | N28: 0 | O28: =SUM(C28:N28) -> 2235.7 | P28: =IFERROR(O28/O4,0) -> 0.0010572804
A29: 6321100 | B29: Asesoria Administrativa | C29: 2300 | D29: 0 | E29: 0 | F29: 252 | G29: 0 | H29: 0 | I29: 0 | J29: 0 | K29: 0 | L29: 0 | M29: 0 | N29: 0 | O29: =SUM(C29:N29) -> 2552 | P29: =IFERROR(O29/O4,0) -> 0.0012068612
A30: 6322100 | B30: Asesoria Legal/Tributaria | C30: 1500 | D30: 0 | E30: 1575 | F30: 0 | G30: 0 | H30: 0 | I30: 0 | J30: 0 | K30: 787.5 | L30: 0 | M30: 0 | N30: 1260 | O30: =SUM(C30:N30) -> 5122.5 | P30: =IFERROR(O30/O4,0) -> 0.0024224711
A31: 6323100 | B31: Auditoria y contable | C31: 2000 | D31: 2000 | E31: 0 | F31: 0 | G31: 4000 | H31: 4000 | I31: 2000 | J31: 2000 | K31: 2000 | L31: 2000 | M31: 2000 | N31: 2000 | O31: =SUM(C31:N31) -> 24000 | P31: =IFERROR(O31/O4,0) -> 0.011349791
A32: 6329100 | B32: Otros Servicios Asesoria | C32: 500 | D32: 3250 | E32: 0 | F32: 0 | G32: 0 | H32: 220 | I32: 0 | J32: 0 | K32: 0 | L32: 0 | M32: 1650 | N32: 2310 | O32: =SUM(C32:N32) -> 7930 | P32: =IFERROR(O32/O4,0) -> 0.0037501603
A33: 6341101 | B33: Mantenimiento Local | C33: 100 | D33: 0 | E33: 142.37 | F33: 1890 | G33: 997.5 | H33: 367.5 | I33: 626.8 | J33: 976.5 | K33: 15398.48 | L33: 735 | M33: 2179.82 | N33: 0 | O33: =SUM(C33:N33) -> 23413.97 | P33: =IFERROR(O33/O4,0) -> 0.011072653
A34: 6343100 | B34: Mant. Prop/Planta/Eq. | C34: 250 | D34: 0 | E34: 0 | F34: 0 | G34: 0 | H34: 0 | I34: 1050 | J34: 0 | K34: 2572.5 | L34: 0 | M34: 0 | N34: 0 | O34: =SUM(C34:N34) -> 3872.5 | P34: =IFERROR(O34/O4,0) -> 0.0018313361
A35: 6352101 | B35: Alquiler Chiller | C35: 19000 | D35: 19000 | E35: 0 | F35: 19000 | G35: 19000 | H35: 19000 | I35: 19000 | J35: 19000 | K35: 19000 | L35: 19000 | M35: 19000 | N35: 19000 | O35: =SUM(C35:N35) -> 209000 | P35: =IFERROR(O35/O4,0) -> 0.098837767
A36: 6352102 | B36: Alquiler Local | C36: 50842.5 | D36: 49882.5 | E36: 50467.05 | F36: 51458.49 | G36: 50893.92 | H36: 49558.23 | I36: 49131.36 | J36: 49475.61 | K36: 48979.89 | L36: 47465.19 | M36: 47671.74 | N36: 47372.37 | O36: =SUM(C36:N36) -> 593198.85 | P36: =IFERROR(O36/O4,0) -> 0.28052847
A37: 6356100 | B37: Alquiler Equipos | C37: 156.78 | D37: 0 | E37: 0 | F37: 313.56 | G37: 0 | H37: 313.56 | I37: 0 | J37: 156.78 | K37: 156.78 | L37: 156.78 | M37: 156.78 | N37: 156.78 | O37: =SUM(C37:N37) -> 1567.8 | P37: =IFERROR(O37/O4,0) -> 0.00074142513
A38: 6361100 | B38: Energia electrica | C38: 22754.51 | D38: 24839.76 | E38: 23900.6 | F38: 23465.44 | G38: 21023.01 | H38: 19337.14 | I38: 18258.2 | J38: 17629.23 | K38: 18321.68 | L38: 17355.6 | M38: 17838.55 | N38: 19557.35 | O38: =SUM(C38:N38) -> 244281.07 | P38: =IFERROR(O38/O4,0) -> 0.11552247
A39: 6363100 | B39: Agua | C39: 1097.03 | D39: 1043.05 | E39: 863.03 | F39: 696.54 | G39: 807.32 | H39: 640.53 | I39: 451.97 | J39: 540.4 | K39: 599.6 | L39: 487.38 | M39: 643.51 | N39: 485.11 | O39: =SUM(C39:N39) -> 8355.47 | P39: =IFERROR(O39/O4,0) -> 0.0039513684
A40: 6365100 | B40: Internet | C40: 184.75 | D40: 184.75 | E40: 0 | F40: 0 | G40: 127.12 | H40: 91.65 | I40: 91.65 | J40: 91.65 | K40: 0 | L40: 91.65 | M40: 91.65 | N40: 178.07 | O40: =SUM(C40:N40) -> 1132.94 | P40: =IFERROR(O40/O4,0) -> 0.00053577636
A41: 6371100 | B41: Publicidad | C41: 0 | D41: 0 | E41: 0 | F41: 0 | G41: 0 | H41: 0 | I41: 0 | J41: 0 | K41: 0 | L41: 0 | M41: 7756.82 | N41: 3600 | O41: =SUM(C41:N41) -> 11356.82 | P41: =IFERROR(O41/O4,0) -> 0.0053707308
A42: 6381100 | B42: Servicios de monitoreo | C42: 1159.16 | D42: 0 | E42: 0 | F42: 18 | G42: 0 | H42: 402.54 | I42: 0 | J42: 1420 | K42: 0 | L42: 0 | M42: 0 | N42: 0 | O42: =SUM(C42:N42) -> 2999.7 | P42: =IFERROR(O42/O4,0) -> 0.0014185821
A43: 6381101 | B43: Servicio informaticos | C43: 0 | D43: 0 | E43: 800 | F43: 0 | G43: 0 | H43: 0 | I43: 0 | J43: 0 | K43: 0 | L43: 0 | M43: 250 | N43: 0 | O43: =SUM(C43:N43) -> 1050 | P43: =IFERROR(O43/O4,0) -> 0.00049655338
A44: 6381102 | B44: Servicio operador | C44: 1200 | D44: 0 | E44: 0 | F44: 0 | G44: 0 | H44: 0 | I44: 0 | J44: 0 | K44: 0 | L44: 0 | M44: 0 | N44: 0 | O44: =SUM(C44:N44) -> 1200 | P44: =IFERROR(O44/O4,0) -> 0.00056748957
A45: 6381103 | B45: Servicios de sistemas | C45: 0 | D45: 0 | E45: 0 | F45: 0 | G45: 0 | H45: 6500 | I45: 0 | J45: 0 | K45: 0 | L45: 0 | M45: 0 | N45: 0 | O45: =SUM(C45:N45) -> 6500 | P45: =IFERROR(O45/O4,0) -> 0.0030739018
A46: 6381104 | B46: Soporte tecnico | C46: 0 | D46: 0 | E46: 0 | F46: 0 | G46: 0 | H46: 0 | I46: 0 | J46: 0 | K46: 0 | L46: 0 | M46: 0 | N46: 156.93 | O46: =SUM(C46:N46) -> 156.93 | P46: =IFERROR(O46/O4,0) -> 7.4213449e-05
A47: 6381105 | B47: Servicios de diseno | C47: 1700 | D47: 1700 | E47: 1700 | F47: 1700 | G47: 1700 | H47: 1729.9 | I47: 1700 | J47: 0 | K47: 0 | L47: 0 | M47: 0 | N47: 0 | O47: =SUM(C47:N47) -> 11929.9 | P47: =IFERROR(O47/O4,0) -> 0.0056417449
A48: 6381108 | B48: Creacion de Contenido | C48: 29.9 | D48: 0 | E48: 65.78 | F48: 65.78 | G48: 0 | H48: 0 | I48: 0 | J48: 0 | K48: 0 | L48: 1558.37 | M48: 0 | N48: 0 | O48: =SUM(C48:N48) -> 1719.83 | P48: =IFERROR(O48/O4,0) -> 0.00081332133
A49: 6381110 | B49: Servicio de Evento | C49: 3008.55 | D49: 2128.44 | E49: 779.67 | F49: 3361.62 | G49: 2609.61 | H49: 3475.96 | I49: 4555.87 | J49: 2555.65 | K49: 1381.47 | L49: 2194.52 | M49: 2957.83 | N49: 4720.69 | O49: =SUM(C49:N49) -> 33729.88 | P49: =IFERROR(O49/O4,0) -> 0.015951129
A50: 6381111 | B50: Servicio de Seguridad | C50: 1040 | D50: 2606.67 | E50: 1785 | F50: 3735.31 | G50: 1903.65 | H50: 2043.99 | I50: 2142 | J50: 951.72 | K50: 0 | L50: 0 | M50: 0 | N50: 420 | O50: =SUM(C50:N50) -> 16628.34 | P50: =IFERROR(O50/O4,0) -> 0.0078636746
A51: 6381112 | B51: Servicios Varios | C51: 100 | D51: 0 | E51: 0 | F51: 0 | G51: 0 | H51: 0 | I51: 0 | J51: 234 | K51: 0 | L51: 375 | M51: 0 | N51: 360 | O51: =SUM(C51:N51) -> 1069 | P51: =IFERROR(O51/O4,0) -> 0.00050553863
A52: 6381114 | B52: Comision Ventas | C52: 1896.54 | D52: 772.04 | E52: 0 | F52: 77 | G52: 374.9 | H52: 216.29 | I52: 90.09 | J52: 432.76 | K52: 207.16 | L52: 3739.87 | M52: 25.36 | N52: 0 | O52: =SUM(C52:N52) -> 7832.01 | P52: =IFERROR(O52/O4,0) -> 0.00370382
A53: 6381115 | B53: Servicio Patinaje | C53: 500 | D53: 0 | E53: 0 | F53: 0 | G53: 0 | H53: 0 | I53: 396 | J53: 660 | K53: 0 | L53: 0 | M53: 0 | N53: 0 | O53: =SUM(C53:N53) -> 1556 | P53: =IFERROR(O53/O4,0) -> 0.00073584481
A54: 6381117 | B54: Servicio Topico | C54: 560 | D54: 240 | E54: 672 | F54: 1450.51 | G54: 651 | H54: 0 | I54: 1648.42 | J54: 525 | K54: 306.55 | L54: 357 | M54: 1163.01 | N54: 315 | O54: =SUM(C54:N54) -> 7888.49 | P54: =IFERROR(O54/O4,0) -> 0.0037305298
A55: 6391100 | B55: Gastos bancarios | C55: 395.43 | D55: 178.6 | E55: 140.37 | F55: 555.38 | G55: 364.4 | H55: 210.23 | I55: 188.2 | J55: 187.15 | K55: 192.87 | L55: 186.36 | M55: 186.63 | N55: 230.47 | O55: =SUM(C55:N55) -> 3016.09 | P55: =IFERROR(O55/O4,0) -> 0.001426333
A56: 6412100 | B56: ITF | C56: 17.17 | D56: 22.63 | E56: 4.84 | F56: 15.22 | G56: 13.73 | H56: 14.82 | I56: 15.68 | J56: 16.84 | K56: 15.5 | L56: 13.6 | M56: 12 | N56: 21.37 | O56: =SUM(C56:N56) -> 183.4 | P56: =IFERROR(O56/O4,0) -> 8.6731323e-05
A57: 6432100 | B57: Arbitrios municipales | C57: 0 | D57: 0 | E57: 0 | F57: 0 | G57: 0 | H57: 0 | I57: 0 | J57: 0 | K57: 0 | L57: 13222.36 | M57: 0 | N57: 0 | O57: =SUM(C57:N57) -> 13222.36 | P57: =IFERROR(O57/O4,0) -> 0.0062529595
A58: 6443100 | B58: Otros Tributos | C58: 0 | D58: 0 | E58: 0 | F58: 0 | G58: 0 | H58: 0 | I58: 0 | J58: 0 | K58: 0 | L58: 0 | M58: 0 | N58: 0 | O58: =SUM(C58:N58) -> 0 | P58: =IFERROR(O58/O4,0) -> 0
A59: 6451100 | B59: Intereses deuda tributaria | C59: 4 | D59: 0 | E59: 0 | F59: 0 | G59: 0 | H59: 0 | I59: 0 | J59: 0 | K59: 0 | L59: 0 | M59: 0 | N59: 0 | O59: =SUM(C59:N59) -> 4 | P59: =IFERROR(O59/O4,0) -> 1.8916319e-06
A60: 6511100 | B60: Seguros | C60: 0 | D60: 0 | E60: 0 | F60: 0 | G60: 0 | H60: 5049.28 | I60: 0 | J60: 0 | K60: 0 | L60: 0 | M60: 0 | N60: 0 | O60: =SUM(C60:N60) -> 5049.28 | P60: =IFERROR(O60/O4,0) -> 0.0023878448
A61: 6531100 | B61: Suscripciones | C61: 0 | D61: 0 | E61: 0 | F61: 0 | G61: 725.81 | H61: 168 | I61: 5379.15 | J61: 188.37 | K61: 185.85 | L61: 0 | M61: 186.45 | N61: 186.07 | O61: =SUM(C61:N61) -> 7019.7 | P61: =IFERROR(O61/O4,0) -> 0.0033196721
A62: 6541100 | B62: Licencias | C62: 0 | D62: 0 | E62: 0 | F62: 0 | G62: 168 | H62: 190.68 | I62: 186.32 | J62: 0 | K62: 0 | L62: 182.07 | M62: 0 | N62: 0 | O62: =SUM(C62:N62) -> 727.07 | P62: =IFERROR(O62/O4,0) -> 0.0003438372
A63: 6551400 | B63: Costo Enajenacion Activos | C63: 0 | D63: 0 | E63: 0 | F63: 0 | G63: 0 | H63: 0 | I63: 0 | J63: 0 | K63: 0 | L63: 0 | M63: 0 | N63: 0 | O63: =SUM(C63:N63) -> 0 | P63: =IFERROR(O63/O4,0) -> 0
A64: 6561100 | B64: Suministros | C64: 2449.14 | D64: 135.59 | E64: 2349.14 | F64: 0 | G64: 0 | H64: 756.36 | I64: 0 | J64: 387.96 | K64: 0 | L64: 818.63 | M64: 0 | N64: 1957.61 | O64: =SUM(C64:N64) -> 8854.43 | P64: =IFERROR(O64/O4,0) -> 0.0041873306
A65: 6561102 | B65: Utiles de Oficina | C65: 689.76 | D65: 355.24 | E65: 47.07 | F65: 69.58 | G65: 162.39 | H65: 40.05 | I65: 60.95 | J65: 381.34 | K65: 620.6 | L65: 26.25 | M65: 171.74 | N65: 8.9 | O65: =SUM(C65:N65) -> 2633.87 | P65: =IFERROR(O65/O4,0) -> 0.0012455781
A66: 6561103 | B66: Utiles de Aseo | C66: 0 | D66: 5.08 | E66: 1317.84 | F66: 1245.76 | G66: 0 | H66: 1066.9 | I66: 965.38 | J66: 979.7 | K66: 411.99 | L66: 758.13 | M66: 969.03 | N66: 0 | O66: =SUM(C66:N66) -> 7719.81 | P66: =IFERROR(O66/O4,0) -> 0.0036507597
A67: 6561104 | B67: Articulos Ferreteria | C67: 409.16 | D67: 110.08 | E67: 754.12 | F67: 256.73 | G67: 151.26 | H67: 10.68 | I67: 401.4 | J67: 662.04 | K67: 165.96 | L67: 26.69 | M67: 1034.41 | N67: 35.59 | O67: =SUM(C67:N67) -> 4018.12 | P67: =IFERROR(O67/O4,0) -> 0.001900201
A68: 6561105 | B68: Gastos Registro Publico | C68: 32.1 | D68: 0 | E68: 185.34 | F68: 0 | G68: 0 | H68: 32.1 | I68: -1 | J68: 0 | K68: 0 | L68: 0 | M68: 0 | N68: 0 | O68: =SUM(C68:N68) -> 248.54 | P68: =IFERROR(O68/O4,0) -> 0.00011753655
A69: 6561106 | B69: Botiquin | C69: 61.86 | D69: 212.12 | E69: 0 | F69: 0 | G69: 15.21 | H69: 32.57 | I69: 62.91 | J69: 20.55 | K69: 26.69 | L69: 0 | M69: 0 | N69: 319.89 | O69: =SUM(C69:N69) -> 751.8 | P69: =IFERROR(O69/O4,0) -> 0.00035553222
A70: 6561107 | B70: Activo Menor | C70: 188.5 | D70: 694.79 | E70: 0 | F70: 183.85 | G70: 0 | H70: 0 | I70: 635.59 | J70: 155.34 | K70: 0 | L70: 0 | M70: 0 | N70: 0 | O70: =SUM(C70:N70) -> 1858.07 | P70: =IFERROR(O70/O4,0) -> 0.00087869612
A71: 6561108 | B71: Gastos Notariales | C71: 0 | D71: 0 | E71: 52.12 | F71: 0 | G71: 0 | H71: 101.69 | I71: 556.36 | J71: 0 | K71: 0 | L71: 0 | M71: 0 | N71: 0 | O71: =SUM(C71:N71) -> 710.17 | P71: =IFERROR(O71/O4,0) -> 0.00033584506
A72: 6561109 | B72: Impresiones y Copias | C72: 157.63 | D72: 0 | E72: 0 | F72: 74.58 | G72: 64.41 | H72: 356.77 | I72: 0 | J72: 0 | K72: 0 | L72: 0 | M72: 0 | N72: 0 | O72: =SUM(C72:N72) -> 653.39 | P72: =IFERROR(O72/O4,0) -> 0.00030899334
A73: 6561110 | B73: Comision Tarjeta | C73: 4317.61 | D73: 4346.69 | E73: 661.82 | F73: 2464.6 | G73: 2531.66 | H73: 3483 | I73: 3747.76 | J73: 5758.52 | K73: 3346.95 | L73: 4912.52 | M73: 3344.25 | N73: 5575.49 | O73: =SUM(C73:N73) -> 44490.87 | P73: =IFERROR(O73/O4,0) -> 0.021040087
A74: 6591103 | B74: Peaje | C74: 0 | D74: 0 | E74: 0 | F74: 0 | G74: 11.18 | H74: 0 | I74: 0 | J74: 0 | K74: 0 | L74: 0 | M74: 0 | N74: 0 | O74: =SUM(C74:N74) -> 11.18 | P74: =IFERROR(O74/O4,0) -> 5.2871112e-06
A75: 6591104 | B75: Gastos a Reparar | C75: 1213 | D75: 22 | E75: 0 | F75: 78.36 | G75: 402 | H75: 200 | I75: 24 | J75: 0 | K75: 1728.1 | L75: 0 | M75: 0 | N75: 0 | O75: =SUM(C75:N75) -> 3667.46 | P75: =IFERROR(O75/O4,0) -> 0.0017343711
A76: 6591105 | B76: Uniformes | C76: 130 | D76: 0 | E76: 181.52 | F76: 75.6 | G76: 52.14 | H76: 0 | I76: 137.04 | J76: 0 | K76: 0 | L76: 0 | M76: 0 | N76: 0 | O76: =SUM(C76:N76) -> 576.3 | P76: =IFERROR(O76/O4,0) -> 0.00027253687
A77: 6591106 | B77: Gastos de Representacion | C77: 0 | D77: 0 | E77: 0 | F77: 0 | G77: 0 | H77: 0 | I77: 0 | J77: 0 | K77: 0 | L77: 0 | M77: 0 | N77: 577.85 | O77: =SUM(C77:N77) -> 577.85 | P77: =IFERROR(O77/O4,0) -> 0.00027326987
A78: 6591107 | B78: Otros Gastos Diversos | C78: 0 | D78: 0 | E78: 0 | F78: 0 | G78: 0 | H78: 2192.44 | I78: 0 | J78: 0 | K78: 0 | L78: 0 | M78: 0 | N78: 0 | O78: =SUM(C78:N78) -> 2192.44 | P78: =IFERROR(O78/O4,0) -> 0.0010368224
A79: 6761100 | B79: Diferencia de cambio | C79: 7150.54 | D79: 2295.87 | E79: 7.1 | F79: 1021.44 | G79: 1080.55 | H79: 1416.8 | I79: 1973.99 | J79: 1217.83 | K79: 1318.71 | L79: 1451.34 | M79: 1179.58 | N79: 4724.56 | O79: =SUM(C79:N79) -> 24838.31 | P79: =IFERROR(O79/O4,0) -> 0.011746235
A80: 6761101 | B80: Diferencia por redondeo | C80: 0 | D80: 0 | E80: 0.32 | F80: 0.7 | G80: 1.3 | H80: 0.04 | I80: 0.02 | J80: 8.09 | K80: 1.05 | L80: 0 | M80: 0.93 | N80: 0.44 | O80: =SUM(C80:N80) -> 12.89 | P80: =IFERROR(O80/O4,0) -> 6.0957838e-06
A81: 6811100 | B81: Dep. Prop. Inv. Edificaciones | C81: 1231.26 | D81: 1231.26 | E81: 0 | F81: 0 | G81: 0 | H81: 0 | I81: 0 | J81: 0 | K81: 0 | L81: 0 | M81: 0 | N81: 0 | O81: =SUM(C81:N81) -> 2462.52 | P81: =IFERROR(O81/O4,0) -> 0.0011645454
A82: 6841200 | B82: Dep. Maquinaria | C82: 135.95 | D82: 135.95 | E82: 0 | F82: 0 | G82: 0 | H82: 0 | I82: 0 | J82: 0 | K82: 0 | L82: 111.02 | M82: 111.02 | N82: 111.02 | O82: =SUM(C82:N82) -> 604.96 | P82: =IFERROR(O82/O4,0) -> 0.00028609041
A83: 6841400 | B83: Dep. Muebles | C83: 199.89 | D83: 199.89 | E83: 0 | F83: 0 | G83: 0 | H83: 0 | I83: 0 | J83: 0 | K83: 0 | L83: 93.82 | M83: 93.82 | N83: 93.82 | O83: =SUM(C83:N83) -> 681.24 | P83: =IFERROR(O83/O4,0) -> 0.00032216383
A84: 6841500 | B84: Dep. Equipos diversos | C84: 401.27 | D84: 401.27 | E84: 0 | F84: 0 | G84: 0 | H84: 0 | I84: 0 | J84: 0 | K84: 26.67 | L84: 206.49 | M84: 206.49 | N84: 206.49 | O84: =SUM(C84:N84) -> 1448.68 | P84: =IFERROR(O84/O4,0) -> 0.00068509233
A85: 6841501 | B85: Dep. Equipos Informaticos | C85: 749 | D85: 749 | E85: 0 | F85: 0 | G85: 0 | H85: 0 | I85: 0 | J85: 0 | K85: 0 | L85: 277.11 | M85: 277.11 | N85: 277.11 | O85: =SUM(C85:N85) -> 2329.33 | P85: =IFERROR(O85/O4,0) -> 0.0011015587
